Workbook

Sheet Assumptions
A1: SierraHomes AmericanDream - Assumptions
A3: Project Name | B3: SierraHomes AmericanDream
A4: Location | B4: Nyali, Mombasa, Kenya
A5: Total Units | B5: 108
A7: Unit Breakdown
A8: 1BR Units | B8: 24
A9: 2BR Units | B9: 36
A10: 3BR Units | B10: 48
A12: Unit Pricing (KES)
A13: 1BR Off-Plan | B13: 10000000
A14: 1BR On-Market | B14: 13000000
A15: 2BR Off-Plan | B15: 17000000
A16: 2BR On-Market | B16: 22000000
A17: 3BR Off-Plan | B17: 23000000
A18: 3BR On-Market | B18: 30000000
A20: Developer Sales Units
A21: 1BR Off-Plan Units | B21: 17
A22: 2BR Off-Plan Units | B22: 28
A23: 3BR Off-Plan Units | B23: 18
A24: 3BR On-Market Units | B24: 22
A26: Project Timeline
A27: Construction Start | B27: 46204
A28: Construction End | B28: 47361
A30: Development Costs (KES)
A31: Hard Costs | B31: 792000000
A32: Soft Costs | B32: 117961921
A33: Total Dev Cost | B33: 909961921
A35: Equity Bridge | B35: 120000000
A37: Payment Milestones (%)
A38: Reservation | B38: 0.1
A39: SPA | B39: 0.2
A40: Foundation | B40: 0.15
A41: Floor3 | B41: 0.1
A42: Floor7 | B42: 0.1
A43: ToppedOut | B43: 0.1
A44: MEP | B44: 0.15
A45: Completion | B45: 0.1

Sheet CashFlow
A1: Month | B1: Jul 2026 | C1: Aug 2026 | D1: Sep 2026 | E1: Oct 2026 | F1: Nov 2026 | G1: Dec 2026 | H1: Jan 2027 | I1: Feb 2027 | J1: Mar 2027 | K1: Apr 2027 | L1: May 2027 | M1: Jun 2027 | N1: Jul 2027 | O1: Aug 2027 | P1: Sep 2027 | Q1: Oct 2027 | R1: Nov 2027 | S1: Dec 2027 | T1: Jan 2028 | U1: Feb 2028 | V1: Mar 2028 | W1: Apr 2028 | X1: May 2028 | Y1: Jun 2028 | Z1: Jul 2028 | AA1: Aug 2028 | AB1: Sep 2028 | AC1: Oct 2028 | AD1: Nov 2028 | AE1: Dec 2028 | AF1: Jan 2029 | AG1: Feb 2029 | AH1: Mar 2029 | AI1: Apr 2029 | AJ1: May 2029 | AK1: Jun 2029 | AL1: Jul 2029 | AM1: Aug 2029 | AN1: Sep 2029 | AO1: Oct 2029 | AP1: Nov 2029 | AQ1: Dec 2029 | AR1: Jan 2030 | AS1: Feb 2030
A2: Month # | B2: 1 | C2: 2 | D2: 3 | E2: 4 | F2: 5 | G2: 6 | H2: 7 | I2: 8 | J2: 9 | K2: 10 | L2: 11 | M2: 12 | N2: 13 | O2: 14 | P2: 15 | Q2: 16 | R2: 17 | S2: 18 | T2: 19 | U2: 20 | V2: 21 | W2: 22 | X2: 23 | Y2: 24 | Z2: 25 | AA2: 26 | AB2: 27 | AC2: 28 | AD2: 29 | AE2: 30 | AF2: 31 | AG2: 32 | AH2: 33 | AI2: 34 | AJ2: 35 | AK2: 36 | AL2: 37 | AM2: 38 | AN2: 39 | AO2: 40 | AP2: 41 | AQ2: 42 | AR2: 43 | AS2: 44
A3: --- INFLOWS ---
A4: Off-Plan Reservation
A5: Off-Plan SPA
A6: Off-Plan Foundation
A7: Off-Plan Floor3
A8: Off-Plan Floor7
A9: Off-Plan ToppedOut
A10: Off-Plan MEP
A11: Off-Plan Completion
A12: On-Market Completion | B12: 0 | C12: 0 | D12: 0 | E12: 0 | F12: 0 | G12: 0 | H12: 0 | I12: 0 | J12: 0 | K12: 0 | L12: 0 | M12: 0 | N12: 0 | O12: 0 | P12: 0 | Q12: 0 | R12: 0 | S12: 0 | T12: 0 | U12: 0 | V12: 0 | W12: 0 | X12: 0 | Y12: 0 | Z12: 0 | AA12: 0 | AB12: 0 | AC12: 0 | AD12: 0 | AE12: 0 | AF12: 0 | AG12: 0 | AH12: 0 | AI12: 0 | AJ12: 0 | AK12: 0 | AL12: =22*30000000/6 -> 110000000 | AM12: =22*30000000/6 -> 110000000 | AN12: =22*30000000/6 -> 110000000 | AO12: =22*30000000/6 -> 110000000 | AP12: =22*30000000/6 -> 110000000 | AQ12: =22*30000000/6 -> 110000000 | AR12: =22*30000000/6 -> 110000000 | AS12: =22*30000000/6 -> 110000000
A14: TOTAL INFLOWS | B14: =SUM(B4:B12) -> 0 | C14: =SUM(C4:C12) -> 0 | D14: =SUM(D4:D12) -> 0 | E14: =SUM(E4:E12) -> 0 | F14: =SUM(F4:F12) -> 0 | G14: =SUM(G4:G12) -> 0 | H14: =SUM(H4:H12) -> 0 | I14: =SUM(I4:I12) -> 0 | ... AS14: =SUM(AS4:AS12) -> 110000000
A16: --- OUTFLOWS ---
A17: Hard Costs | B17: =792000000*0.025 -> 19800000 | C17: =792000000*0.025 -> 19800000 | D17: =792000000*0.025 -> 19800000 | E17: =792000000*0.025 -> 19800000 | F17: =792000000*0.025 -> 19800000 | G17: =792000000*0.025 -> 19800000 | H17: =792000000*0.025 -> 19800000 | I17: =792000000*0.025 -> 19800000 | ... K17: =792000000*0.025 -> 19800000 | L17: =792000000*0.0288461538461538 -> 22846154 | M17: =792000000*0.0288461538461538 -> 22846154 | N17: =792000000*0.0288461538461538 -> 22846154 | O17: =792000000*0.0288461538461538 -> 22846154 | P17: =792000000*0.0288461538461538 -> 22846154 | Q17: =792000000*0.0288461538461538 -> 22846154 | R17: =792000000*0.0288461538461538 -> 22846154 | S17: =792000000*0.0288461538461538 -> 22846154 | ... AK17: =792000000*0.0288461538461538 -> 22846154 | AL17: 0 | AM17: 0 | AN17: 0 | AO17: 0 | AP17: 0 | AQ17: 0 | AR17: 0 | AS17: 0
A18: Soft Costs | B18: =117961921/6 -> 19660320 | C18: =117961921/6 -> 19660320 | D18: =117961921/6 -> 19660320 | E18: =117961921/6 -> 19660320 | F18: =117961921/6 -> 19660320 | G18: =117961921/6 -> 19660320 | H18: 0 | I18: 0 | J18: 0 | K18: 0 | L18: 0 | M18: 0 | N18: 0 | O18: 0 | P18: 0 | Q18: 0 | R18: 0 | S18: 0 | T18: 0 | U18: 0 | V18: 0 | W18: 0 | X18: 0 | Y18: 0 | Z18: 0 | AA18: 0 | AB18: 0 | AC18: 0 | AD18: 0 | AE18: 0 | AF18: 0 | AG18: 0 | AH18: 0 | AI18: 0 | AJ18: 0 | AK18: 0 | AL18: 0 | AM18: 0 | AN18: 0 | AO18: 0 | AP18: 0 | AQ18: 0 | AR18: 0 | AS18: 0
A20: TOTAL OUTFLOWS | B20: =SUM(B17:B18) -> 39460320 | C20: =SUM(C17:C18) -> 39460320 | D20: =SUM(D17:D18) -> 39460320 | E20: =SUM(E17:E18) -> 39460320 | F20: =SUM(F17:F18) -> 39460320 | G20: =SUM(G17:G18) -> 39460320 | H20: =SUM(H17:H18) -> 19800000 | I20: =SUM(I17:I18) -> 19800000 | ... AS20: =SUM(AS17:AS18) -> 0
A22: NET CASH FLOW | B22: =B14-B20 -> -39460320 | C22: =C14-C20 -> -39460320 | D22: =D14-D20 -> -39460320 | E22: =E14-E20 -> -39460320 | F22: =F14-F20 -> -39460320 | G22: =G14-G20 -> -39460320 | H22: =H14-H20 -> -19800000 | I22: =I14-I20 -> -19800000 | ... AS22: =AS14-AS20 -> 110000000
A23: CUMULATIVE CASH FLOW | B23: =B22 -> -39460320 | C23: =B23+C22 -> -78920640 | D23: =C23+D22 -> -1.1838096e+08 | E23: =D23+E22 -> -1.5784128e+08 | F23: =E23+F22 -> -1.973016e+08 | G23: =F23+G22 -> -236761921 | H23: =G23+H22 -> -256561921 | I23: =H23+I22 -> -276361921 | J23: =I23+J22 -> -296161921 | ... AS23: =AR23+AS22 -> -29961921
A25: Equity Drawn (Bridge) | B25: 20000000 | C25: 20000000 | D25: 20000000 | E25: 20000000 | F25: 20000000 | G25: 20000000 | H25: 0 | I25: 0 | J25: 0 | K25: 0 | L25: 0 | M25: 0 | N25: 0 | O25: 0 | P25: 0 | Q25: 0 | R25: 0 | S25: 0 | T25: 0 | U25: 0 | V25: 0 | W25: 0 | X25: 0 | Y25: 0 | Z25: 0 | AA25: 0 | AB25: 0 | AC25: 0 | AD25: 0 | AE25: 0 | AF25: 0 | AG25: 0 | AH25: 0 | AI25: 0 | AJ25: 0 | AK25: 0 | AL25: 0 | AM25: 0 | AN25: 0 | AO25: 0 | AP25: 0 | AQ25: 0 | AR25: 0 | AS25: 0

Sheet Summary
A1: SierraHomes AmericanDream - Financial Summary
A3: Off-Plan Revenue
A4: 1BR Off-Plan | B4: =Assumptions!B21*Assumptions!B13 -> 170000000
A5: 2BR Off-Plan | B5: =Assumptions!B22*Assumptions!B15 -> 476000000
A6: 3BR Off-Plan | B6: =Assumptions!B23*Assumptions!B17 -> 414000000
A7: Total Off-Plan Revenue | B7: =B4+B5+B6 -> 1060000000
A9: On-Market Revenue
A10: 3BR On-Market | B10: =Assumptions!B24*Assumptions!B18 -> 660000000
A12: TOTAL GROSS REVENUE | B12: =B7+B10 -> 1720000000
A14: Total Development Cost | B14: =Assumptions!B33 -> 909961921
A16: NET PROFIT | B16: =B12-B14 -> 810038079
A18: ROI (%) | B18: =B16/B14 -> 0.89018899
A20: Peak Equity Drawn | B20: =Assumptions!B32 -> 117961921
