Workbook

Sheet Assumptions
A1: Investor Returns - Assumptions
A3: Equity Amount (KES) | B3: 120000000
A5: Preferred Return (%) | B5: 0.12
A6: Hold Period (years) | B6: 3.5
A8: Profit Share Scenarios
A9: Scenario 1 (%) | B9: 0.1
A10: Scenario 2 (%) | B10: 0.2
A11: Scenario 3 (%) | B11: 0.3
A13: Total Gross Revenue (KES) | B13: 1720000000
A14: Total Dev Cost (KES) | B14: 909961921
A15: Net Profit (KES) | B15: =B13-B14 -> 810038079

Sheet Return Waterfall
A1: Return Waterfall Analysis
A3: Item | B3: Scenario 1 (10%) | C3: Scenario 2 (20%) | D3: Scenario 3 (30%)
A4: Equity In | B4: =Assumptions!B3 -> 120000000 | C4: =Assumptions!B3 -> 120000000 | D4: =Assumptions!B3 -> 120000000
A5: Preferred Return (12% × 3.5yr) | B5: =Assumptions!B3*Assumptions!B5*Assumptions!B6 -> 50400000 | C5: =Assumptions!B3*Assumptions!B5*Assumptions!B6 -> 50400000 | D5: =Assumptions!B3*Assumptions!B5*Assumptions!B6 -> 50400000
A6: Profit Share | B6: =(Assumptions!B13-Assumptions!B14)*Assumptions!B9 -> 81003808 | C6: =(Assumptions!B13-Assumptions!B14)*Assumptions!B10 -> 1.6200762e+08 | D6: =(Assumptions!B13-Assumptions!B14)*Assumptions!B11 -> 2.4301142e+08
A7: Total Return (Preferred + Share) | B7: =B5+B6 -> 1.3140381e+08 | C7: =C5+C6 -> 2.1240762e+08 | D7: =D5+D6 -> 2.9341142e+08
A8: Return of Capital | B8: =Assumptions!B3 -> 120000000 | C8: =Assumptions!B3 -> 120000000 | D8: =Assumptions!B3 -> 120000000
A9: TOTAL CASH RETURNED | B9: =B7+B8 -> 2.5140381e+08 | C9: =C7+C8 -> 3.3240762e+08 | D9: =D7+D8 -> 4.1341142e+08
A11: ROC (Return on Capital %) | B11: =B7/Assumptions!B3 -> 1.0950317 | C11: =C7/Assumptions!B3 -> 1.7700635 | D11: =D7/Assumptions!B3 -> 2.4450952
A12: Net Profit to Investor | B12: =B7-Assumptions!$B$2 -> 1.3140381e+08 | C12: =C7-Assumptions!$B$2 -> 2.1240762e+08 | D12: =D7-Assumptions!$B$2 -> 2.9341142e+08

Sheet IRR Analysis
A1: IRR Analysis
A3: Year | B3: Cash Flow (KES)
A4: 0 | B4: =-Assumptions!B3 -> -120000000
A5: 1 | B5: 0
A6: 2 | B6: 0
A7: 3 (Scenario 1) | B7: =('Return Waterfall'!B7 + 'Return Waterfall'!B8) -> 2.5140381e+08
A9: XIRR (Scenario 1) | B9: =IRR(B4:B7) -> 0.27956849
A11: NPV @ 15% discount | B11: =NPV(0.15,B5:B7)+B4 -> 45302085
A12: NPV @ 20% discount | B12: =NPV(0.2,B5:B7)+B4 -> 25488315
