Workbook

Sheet Cover
B2: MSIFS — Frontier Impact Infrastructure & Minerals Fund
B3: Multi-Dimensional Infrastructure Project Finance Model
B5: Model Version 1.0 | February 2026
B9: MODEL ARCHITECTURE
B10: Sheet | C10: Purpose
B11: 1. Cover | C11: This page — overview and instructions
B12: 2. Assumptions | C12: All hardcoded inputs: project type toggles, macro assumptions, financing terms
B13: 3. Revenue Build | C13: Revenue projections by project type with commodity price scenarios
B14: 4. CAPEX Schedule | C14: Construction & development cost phasing with contingency
B15: 5. OPEX Schedule | C15: Operating cost buildup with escalation and FX impact
B16: 6. Financing Structure | C16: Multi-tranche debt & equity waterfall with currency layers
B17: 7. Cash Flow Waterfall | C17: Integrated cash flow statement with DSCR and LLCR
B18: 8. Currency & FX | C18: Cross-border FX modeling, hedging costs, local currency swaps
B19: 9. Returns Analysis | C19: IRR, NPV, MOIC, payback for equity and project-level returns
B20: 10. Exit Scenarios | C20: Multiple exit paths: trade sale, IPO, recap, strategic, liquidation
B21: 11. Sensitivity | C21: Tornado charts data, scenario matrix, Monte Carlo input ranges
B22: 12. Impact Metrics | C22: IRIS+ aligned impact KPIs and impact-linked carry calculation
B24: COLOR CODING CONVENTIONS
B25: Blue text | C25: Hardcoded inputs — user modifiable
B26: Black text | C26: Formulas and calculations
B27: Green text | C27: Cross-sheet references
B28: Yellow highlight | C28: Key assumptions requiring attention

Sheet Assumptions
B1: GLOBAL ASSUMPTIONS & PROJECT PARAMETERS
B3: PROJECT TYPE SELECTOR
B4: Project Type Toggle (1-6) | C4: 1
B5: 1 = Port & Logistics Infrastructure | C5: Lamu Port, Maputo, Grain Elevators
B6: 2 = Mining & Mineral Processing | C6: Lithium, Copper, Rare Earth, Gold
B7: 3 = Energy & Power Generation | C7: Solar, Wind, Hybrid, Gas-to-Power
B8: 4 = Transport Corridors | C8: Toll Roads, Railways, LAPSSET
B9: 5 = LNG & Gas Infrastructure | C9: Mtwara LNG, Virtual Pipelines, CNG
B10: 6 = Agri-Processing & Value Chain | C10: Grain Handling, Cold Storage, Fertilizer
B12: MACRO & COUNTRY ASSUMPTIONS
B13: Parameter | C13: Base Case | D13: Downside | E13: Upside | F13: Unit
B14: Country Risk Premium | C14: 0.045 | D14: 0.065 | E14: 0.03 | F14: %
B15: Sovereign Credit Spread (bps) | C15: 350 | D15: 550 | E15: 200 | F15: bps
B16: Local Inflation Rate | C16: 0.07 | D16: 0.12 | E16: 0.04 | F16: %
B17: USD Inflation Rate | C17: 0.025 | D17: 0.04 | E17: 0.02 | F17: %
B18: Local Currency Depr. Rate (annual) | C18: 0.05 | D18: 0.1 | E18: 0.02 | F18: %
B19: Political Risk Insurance Cost | C19: 0.015 | D19: 0.025 | E19: 0.01 | F19: %
B20: Corporate Tax Rate (host) | C20: 0.3 | D20: 0.35 | E20: 0.25 | F20: %
B21: Withholding Tax on Dividends | C21: 0.1 | D21: 0.15 | E21: 0.05 | F21: %
B22: VAT Rate | C22: 0.16 | D22: 0.18 | E22: 0.14 | F22: %
B23: Tax Holiday (years) | C23: 5 | D23: 0 | E23: 10 | F23: yrs
B24: WACC — Risk-Free Rate (USD) | C24: 0.045 | D24: 0.055 | E24: 0.035 | F24: %
B25: Equity Risk Premium | C25: 0.065 | D25: 0.085 | E25: 0.05 | F25: %
B26: Target Gross IRR | C26: 0.17 | D26: 0.13 | E26: 0.22 | F26: %
B28: PROJECT-LEVEL ASSUMPTIONS
B29: Parameter | C29: Base Case | D29: Downside | E29: Upside | F29: Unit
B30: Total Project Cost ($M) | C30: 50 | D30: 30 | E30: 100 | F30: $M
B31: Construction Period (months) | C31: 24 | D31: 36 | E31: 18 | F31: mo
B32: Operating Life (years) | C32: 20 | D32: 15 | E32: 25 | F32: yrs
B33: Fund Investment ($M) | C33: 15 | D33: 8 | E33: 25 | F33: $M
B34: Equity Stake (%) | C34: 0.3 | D34: 0.2 | E34: 0.49 | F34: %
B35: Revenue Ramp-Up (years to full) | C35: 3 | D35: 5 | E35: 2 | F35: yrs
B36: Steady-State Utilization | C36: 0.85 | D36: 0.7 | E36: 0.95 | F36: %
B37: Annual Revenue at Full Capacity ($M) | C37: 25 | D37: 15 | E37: 40 | F37: $M
B38: OPEX as % of Revenue | C38: 0.45 | D38: 0.55 | E38: 0.35 | F38: %
B39: Annual OPEX Escalation | C39: 0.04 | D39: 0.07 | E39: 0.025 | F39: %
B40: Maintenance CAPEX (% of initial) | C40: 0.02 | D40: 0.035 | E40: 0.015 | F40: %
B41: Working Capital (days of revenue) | C41: 60 | D41: 90 | E41: 45 | F41: days
B42: Contingency (% of CAPEX) | C42: 0.1 | D42: 0.15 | E42: 0.05 | F42: %
B44: FINANCING STRUCTURE
B45: Parameter | C45: Base Case | D45: Downside | E45: Upside | F45: Unit
B46: Senior Debt (% of Project Cost) | C46: 0.55 | D46: 0.45 | E46: 0.65 | F46: %
B47: Senior Debt Tenor (years) | C47: 12 | D47: 10 | E47: 15 | F47: yrs
B48: Senior Debt Interest Rate | C48: 0.085 | D48: 0.1 | E48: 0.07 | F48: %
B49: Senior Debt Grace Period (years) | C49: 2 | D49: 1 | E49: 3 | F49: yrs
B50: Mezzanine Debt (% of Project Cost) | C50: 0.1 | D50: 0.05 | E50: 0.15 | F50: %
B51: Mezzanine Rate | C51: 0.13 | D51: 0.15 | E51: 0.11 | F51: %
B52: DFI/Concessional Layer (% of Cost) | C52: 0.1 | D52: 0.05 | E52: 0.15 | F52: %
B53: DFI Interest Rate | C53: 0.04 | D53: 0.05 | E53: 0.03 | F53: %
B54: DFI Tenor (years) | C54: 20 | D54: 15 | E54: 25 | F54: yrs
B55: Equity Contribution (% of Cost) | C55: 0.25 | D55: 0.35 | E55: 0.2 | F55: %
B56: Debt Arrangement Fee | C56: 0.02 | D56: 0.03 | E56: 0.015 | F56: %
B57: Commitment Fee on Undrawn | C57: 0.005 | D57: 0.0075 | E57: 0.004 | F57: %
... B60: Lock-Up DSCR | C60: 1.1 | D60: 1.05 | E60: 1.15 | F60: x
B62: COMMODITY PRICE ASSUMPTIONS (for Mining/LNG toggles)
B63: Commodity | C63: Base Case | D63: Bear | E63: Bull | F63: Unit
B64: Copper ($/tonne) | C64: 9500 | D64: 7000 | E64: 12000 | F64: $/t
B65: Lithium Carbonate ($/tonne) | C65: 22000 | D65: 12000 | E65: 35000 | F65: $/t
B66: Gold ($/oz) | C66: 2400 | D66: 1800 | E66: 3000 | F66: $/oz
B67: Rare Earth Oxide Basket ($/kg) | C67: 45 | D67: 30 | E67: 75 | F67: $/kg
B68: LNG ($/MMBtu) | C68: 12 | D68: 8 | E68: 18 | F68: $/MMBtu
B69: CNG ($/MMBtu) | C69: 8 | D69: 5 | E69: 12 | F69: $/MMBtu
B70: Annual Commodity Price Escalation | C70: 0.02 | D70: -0.01 | E70: 0.04 | F70: %

Sheet Revenue Build
B1: REVENUE PROJECTIONS — 20-YEAR OPERATING HORIZON
B3: Year | C3: Unit | D3: 1 | E3: 2 | F3: 3 | G3: 4 | H3: 5 | I3: 6 | J3: 7 | K3: 8 | L3: 9 | M3: 10 | N3: 11 | O3: 12 | P3: 13 | Q3: 14 | R3: 15 | S3: 16 | T3: 17 | U3: 18 | V3: 19 | W3: 20
B4: REVENUE DRIVERS
B5: Capacity Utilization Ramp | C5: % | D5: =IF(1<=Assumptions!C31/12,0,MIN(Assumptions!C36,MAX(0,1-Assumptions!C31/12)/Assumptions!C35)) -> 0 | E5: =IF(2<=Assumptions!C31/12,0,MIN(Assumptions!C36,MAX(0,2-Assumptions!C31/12)/Assumptions!C35)) -> 0 | F5: =IF(3<=Assumptions!C31/12,0,MIN(Assumptions!C36,MAX(0,3-Assumptions!C31/12)/Assumptions!C35)) -> 0.33333333 | G5: =IF(4<=Assumptions!C31/12,0,MIN(Assumptions!C36,MAX(0,4-Assumptions!C31/12)/Assumptions!C35)) -> 0.66666667 | H5: =IF(5<=Assumptions!C31/12,0,MIN(Assumptions!C36,MAX(0,5-Assumptions!C31/12)/Assumptions!C35)) -> 0.85 | I5: =IF(6<=Assumptions!C31/12,0,MIN(Assumptions!C36,MAX(0,6-Assumptions!C31/12)/Assumptions!C35)) -> 0.85 | J5: =IF(7<=Assumptions!C31/12,0,MIN(Assumptions!C36,MAX(0,7-Assumptions!C31/12)/Assumptions!C35)) -> 0.85 | K5: =IF(8<=Assumptions!C31/12,0,MIN(Assumptions!C36,MAX(0,8-Assumptions!C31/12)/Assumptions!C35)) -> 0.85 | L5: =IF(9<=Assumptions!C31/12,0,MIN(Assumptions!C36,MAX(0,9-Assumptions!C31/12)/Assumptions!C35)) -> 0.85 | M5: =IF(10<=Assumptions!C31/12,0,MIN(Assumptions!C36,MAX(0,10-Assumptions!C31/12)/Assumptions!C35)) -> 0.85 | N5: =IF(11<=Assumptions!C31/12,0,MIN(Assumptions!C36,MAX(0,11-Assumptions!C31/12)/Assumptions!C35)) -> 0.85 | O5: =IF(12<=Assumptions!C31/12,0,MIN(Assumptions!C36,MAX(0,12-Assumptions!C31/12)/Assumptions!C35)) -> 0.85 | P5: =IF(13<=Assumptions!C31/12,0,MIN(Assumptions!C36,MAX(0,13-Assumptions!C31/12)/Assumptions!C35)) -> 0.85 | Q5: =IF(14<=Assumptions!C31/12,0,MIN(Assumptions!C36,MAX(0,14-Assumptions!C31/12)/Assumptions!C35)) -> 0.85 | R5: =IF(15<=Assumptions!C31/12,0,MIN(Assumptions!C36,MAX(0,15-Assumptions!C31/12)/Assumptions!C35)) -> 0.85 | S5: =IF(16<=Assumptions!C31/12,0,MIN(Assumptions!C36,MAX(0,16-Assumptions!C31/12)/Assumptions!C35)) -> 0.85 | T5: =IF(17<=Assumptions!C31/12,0,MIN(Assumptions!C36,MAX(0,17-Assumptions!C31/12)/Assumptions!C35)) -> 0.85 | U5: =IF(18<=Assumptions!C31/12,0,MIN(Assumptions!C36,MAX(0,18-Assumptions!C31/12)/Assumptions!C35)) -> 0.85 | V5: =IF(19<=Assumptions!C31/12,0,MIN(Assumptions!C36,MAX(0,19-Assumptions!C31/12)/Assumptions!C35)) -> 0.85 | W5: =IF(20<=Assumptions!C31/12,0,MIN(Assumptions!C36,MAX(0,20-Assumptions!C31/12)/Assumptions!C35)) -> 0.85
B6: Gross Revenue (Base, $M) | C6: $M | D6: =Assumptions!C37*D5 -> 0 | E6: =Assumptions!C37*E5 -> 0 | F6: =Assumptions!C37*F5 -> 8.3333333 | G6: =Assumptions!C37*G5 -> 16.666667 | H6: =Assumptions!C37*H5 -> 21.25 | I6: =Assumptions!C37*I5 -> 21.25 | J6: =Assumptions!C37*J5 -> 21.25 | K6: =Assumptions!C37*K5 -> 21.25 | L6: =Assumptions!C37*L5 -> 21.25 | M6: =Assumptions!C37*M5 -> 21.25 | N6: =Assumptions!C37*N5 -> 21.25 | O6: =Assumptions!C37*O5 -> 21.25 | P6: =Assumptions!C37*P5 -> 21.25 | Q6: =Assumptions!C37*Q5 -> 21.25 | R6: =Assumptions!C37*R5 -> 21.25 | S6: =Assumptions!C37*S5 -> 21.25 | T6: =Assumptions!C37*T5 -> 21.25 | U6: =Assumptions!C37*U5 -> 21.25 | V6: =Assumptions!C37*V5 -> 21.25 | W6: =Assumptions!C37*W5 -> 21.25
B7: Commodity Price Adjustment Factor | C7: x | D7: =IF(D5=0,0,(1+Assumptions!C70)^MAX(0,1-Assumptions!C31/12)) -> 0 | E7: =IF(E5=0,0,(1+Assumptions!C70)^MAX(0,2-Assumptions!C31/12)) -> 0 | F7: =IF(F5=0,0,(1+Assumptions!C70)^MAX(0,3-Assumptions!C31/12)) -> 1.02 | G7: =IF(G5=0,0,(1+Assumptions!C70)^MAX(0,4-Assumptions!C31/12)) -> 1.0404 | H7: =IF(H5=0,0,(1+Assumptions!C70)^MAX(0,5-Assumptions!C31/12)) -> 1.061208 | I7: =IF(I5=0,0,(1+Assumptions!C70)^MAX(0,6-Assumptions!C31/12)) -> 1.0824322 | J7: =IF(J5=0,0,(1+Assumptions!C70)^MAX(0,7-Assumptions!C31/12)) -> 1.1040808 | K7: =IF(K5=0,0,(1+Assumptions!C70)^MAX(0,8-Assumptions!C31/12)) -> 1.1261624 | L7: =IF(L5=0,0,(1+Assumptions!C70)^MAX(0,9-Assumptions!C31/12)) -> 1.1486857 | M7: =IF(M5=0,0,(1+Assumptions!C70)^MAX(0,10-Assumptions!C31/12)) -> 1.1716594 | N7: =IF(N5=0,0,(1+Assumptions!C70)^MAX(0,11-Assumptions!C31/12)) -> 1.1950926 | O7: =IF(O5=0,0,(1+Assumptions!C70)^MAX(0,12-Assumptions!C31/12)) -> 1.2189944 | P7: =IF(P5=0,0,(1+Assumptions!C70)^MAX(0,13-Assumptions!C31/12)) -> 1.2433743 | Q7: =IF(Q5=0,0,(1+Assumptions!C70)^MAX(0,14-Assumptions!C31/12)) -> 1.2682418 | R7: =IF(R5=0,0,(1+Assumptions!C70)^MAX(0,15-Assumptions!C31/12)) -> 1.2936066 | S7: =IF(S5=0,0,(1+Assumptions!C70)^MAX(0,16-Assumptions!C31/12)) -> 1.3194788 | T7: =IF(T5=0,0,(1+Assumptions!C70)^MAX(0,17-Assumptions!C31/12)) -> 1.3458683 | U7: =IF(U5=0,0,(1+Assumptions!C70)^MAX(0,18-Assumptions!C31/12)) -> 1.3727857 | V7: =IF(V5=0,0,(1+Assumptions!C70)^MAX(0,19-Assumptions!C31/12)) -> 1.4002414 | W7: =IF(W5=0,0,(1+Assumptions!C70)^MAX(0,20-Assumptions!C31/12)) -> 1.4282462
B8: FX-Adjusted Revenue ($M, USD) | C8: $M | D8: =IF(D5=0,0,D6*D7*('Currency & FX'!D11+'Currency & FX'!D12*(1/(1+Assumptions!C18)^MAX(0,1-Assumptions!C31/12)))) -> 0 | E8: =IF(E5=0,0,E6*E7*('Currency & FX'!E11+'Currency & FX'!E12*(1/(1+Assumptions!C18)^MAX(0,2-Assumptions!C31/12)))) -> 0 | F8: =IF(F5=0,0,F6*F7*('Currency & FX'!F11+'Currency & FX'!F12*(1/(1+Assumptions!C18)^MAX(0,3-Assumptions!C31/12)))) -> 8.3380952 | G8: =IF(G5=0,0,G6*G7*('Currency & FX'!G11+'Currency & FX'!G12*(1/(1+Assumptions!C18)^MAX(0,4-Assumptions!C31/12)))) -> 16.695156 | H8: =IF(H5=0,0,H6*H7*('Currency & FX'!H11+'Currency & FX'!H12*(1/(1+Assumptions!C18)^MAX(0,5-Assumptions!C31/12)))) -> 21.322449 | I8: =IF(I5=0,0,I6*I7*('Currency & FX'!I11+'Currency & FX'!I12*(1/(1+Assumptions!C18)^MAX(0,6-Assumptions!C31/12)))) -> 21.370427 | J8: =IF(J5=0,0,J6*J7*('Currency & FX'!J11+'Currency & FX'!J12*(1/(1+Assumptions!C18)^MAX(0,7-Assumptions!C31/12)))) -> 21.430178 | K8: =IF(K5=0,0,K6*K7*('Currency & FX'!K11+'Currency & FX'!K12*(1/(1+Assumptions!C18)^MAX(0,8-Assumptions!C31/12)))) -> 21.501629 | L8: =IF(L5=0,0,L6*L7*('Currency & FX'!L11+'Currency & FX'!L12*(1/(1+Assumptions!C18)^MAX(0,9-Assumptions!C31/12)))) -> 21.584713 | M8: =IF(M5=0,0,M6*M7*('Currency & FX'!M11+'Currency & FX'!M12*(1/(1+Assumptions!C18)^MAX(0,10-Assumptions!C31/12)))) -> 21.679371 | N8: =IF(N5=0,0,N6*N7*('Currency & FX'!N11+'Currency & FX'!N12*(1/(1+Assumptions!C18)^MAX(0,11-Assumptions!C31/12)))) -> 21.785553 | O8: =IF(O5=0,0,O6*O7*('Currency & FX'!O11+'Currency & FX'!O12*(1/(1+Assumptions!C18)^MAX(0,12-Assumptions!C31/12)))) -> 21.903212 | P8: =IF(P5=0,0,P6*P7*('Currency & FX'!P11+'Currency & FX'!P12*(1/(1+Assumptions!C18)^MAX(0,13-Assumptions!C31/12)))) -> 22.032312 | Q8: =IF(Q5=0,0,Q6*Q7*('Currency & FX'!Q11+'Currency & FX'!Q12*(1/(1+Assumptions!C18)^MAX(0,14-Assumptions!C31/12)))) -> 22.172821 | R8: =IF(R5=0,0,R6*R7*('Currency & FX'!R11+'Currency & FX'!R12*(1/(1+Assumptions!C18)^MAX(0,15-Assumptions!C31/12)))) -> 22.324716 | S8: =IF(S5=0,0,S6*S7*('Currency & FX'!S11+'Currency & FX'!S12*(1/(1+Assumptions!C18)^MAX(0,16-Assumptions!C31/12)))) -> 22.487979 | T8: =IF(T5=0,0,T6*T7*('Currency & FX'!T11+'Currency & FX'!T12*(1/(1+Assumptions!C18)^MAX(0,17-Assumptions!C31/12)))) -> 22.6626 | U8: =IF(U5=0,0,U6*U7*('Currency & FX'!U11+'Currency & FX'!U12*(1/(1+Assumptions!C18)^MAX(0,18-Assumptions!C31/12)))) -> 22.848574 | V8: =IF(V5=0,0,V6*V7*('Currency & FX'!V11+'Currency & FX'!V12*(1/(1+Assumptions!C18)^MAX(0,19-Assumptions!C31/12)))) -> 23.045904 | W8: =IF(W5=0,0,W6*W7*('Currency & FX'!W11+'Currency & FX'!W12*(1/(1+Assumptions!C18)^MAX(0,20-Assumptions!C31/12)))) -> 23.254599
B10: OPERATING REVENUE DETAIL
B11: Primary Revenue Stream ($M) | C11: $M | D11: =IF(D5=0,0,D8*0.85) -> 0 | E11: =IF(E5=0,0,E8*0.85) -> 0 | F11: =IF(F5=0,0,F8*0.85) -> 7.087381 | G11: =IF(G5=0,0,G8*0.85) -> 14.190883 | H11: =IF(H5=0,0,H8*0.85) -> 18.124081 | I11: =IF(I5=0,0,I8*0.85) -> 18.164863 | J11: =IF(J5=0,0,J8*0.85) -> 18.215651 | K11: =IF(K5=0,0,K8*0.85) -> 18.276384 | ... W11: =IF(W5=0,0,W8*0.85) -> 19.766409
B12: Secondary/By-product Revenue ($M) | C12: $M | D12: =IF(D5=0,0,D8*0.1) -> 0 | E12: =IF(E5=0,0,E8*0.1) -> 0 | F12: =IF(F5=0,0,F8*0.1) -> 0.83380952 | G12: =IF(G5=0,0,G8*0.1) -> 1.6695156 | H12: =IF(H5=0,0,H8*0.1) -> 2.1322449 | I12: =IF(I5=0,0,I8*0.1) -> 2.1370427 | J12: =IF(J5=0,0,J8*0.1) -> 2.1430178 | K12: =IF(K5=0,0,K8*0.1) -> 2.1501629 | ... W12: =IF(W5=0,0,W8*0.1) -> 2.3254599
B13: Offtake/Tolling Revenue ($M) | C13: $M | D13: =IF(D5=0,0,D8*0.05) -> 0 | E13: =IF(E5=0,0,E8*0.05) -> 0 | F13: =IF(F5=0,0,F8*0.05) -> 0.41690476 | G13: =IF(G5=0,0,G8*0.05) -> 0.83475782 | H13: =IF(H5=0,0,H8*0.05) -> 1.0661224 | I13: =IF(I5=0,0,I8*0.05) -> 1.0685213 | J13: =IF(J5=0,0,J8*0.05) -> 1.0715089 | K13: =IF(K5=0,0,K8*0.05) -> 1.0750814 | ... W13: =IF(W5=0,0,W8*0.05) -> 1.16273
B14: Government Subsidy/Grant Income ($M) | C14: $M | D14: 0 | E14: 0 | F14: 0 | G14: 0 | H14: 0 | I14: 0 | J14: 0 | K14: 0 | L14: 0 | M14: 0 | N14: 0 | O14: 0 | P14: 0 | Q14: 0 | R14: 0 | S14: 0 | T14: 0 | U14: 0 | V14: 0 | W14: 0
B15: Total Gross Revenue ($M) | C15: $M | D15: =SUM(D11:D14) -> 0 | E15: =SUM(E11:E14) -> 0 | F15: =SUM(F11:F14) -> 8.3380952 | G15: =SUM(G11:G14) -> 16.695156 | H15: =SUM(H11:H14) -> 21.322449 | I15: =SUM(I11:I14) -> 21.370427 | J15: =SUM(J11:J14) -> 21.430178 | K15: =SUM(K11:K14) -> 21.501629 | ... W15: =SUM(W11:W14) -> 23.254599
B17: REVENUE ADJUSTMENTS
B18: Withholding Tax on Gross Revenue | C18: $M | D18: =IF(D15=0,0,-D15*Assumptions!C21) -> 0 | E18: =IF(E15=0,0,-E15*Assumptions!C21) -> 0 | F18: =IF(F15=0,0,-F15*Assumptions!C21) -> -0.83380952 | G18: =IF(G15=0,0,-G15*Assumptions!C21) -> -1.6695156 | H18: =IF(H15=0,0,-H15*Assumptions!C21) -> -2.1322449 | I18: =IF(I15=0,0,-I15*Assumptions!C21) -> -2.1370427 | J18: =IF(J15=0,0,-J15*Assumptions!C21) -> -2.1430178 | K18: =IF(K15=0,0,-K15*Assumptions!C21) -> -2.1501629 | L18: =IF(L15=0,0,-L15*Assumptions!C21) -> -2.1584713 | M18: =IF(M15=0,0,-M15*Assumptions!C21) -> -2.1679371 | N18: =IF(N15=0,0,-N15*Assumptions!C21) -> -2.1785553 | O18: =IF(O15=0,0,-O15*Assumptions!C21) -> -2.1903212 | P18: =IF(P15=0,0,-P15*Assumptions!C21) -> -2.2032312 | Q18: =IF(Q15=0,0,-Q15*Assumptions!C21) -> -2.2172821 | R18: =IF(R15=0,0,-R15*Assumptions!C21) -> -2.2324716 | S18: =IF(S15=0,0,-S15*Assumptions!C21) -> -2.2487979 | T18: =IF(T15=0,0,-T15*Assumptions!C21) -> -2.26626 | U18: =IF(U15=0,0,-U15*Assumptions!C21) -> -2.2848574 | V18: =IF(V15=0,0,-V15*Assumptions!C21) -> -2.3045904 | W18: =IF(W15=0,0,-W15*Assumptions!C21) -> -2.3254599
B19: VAT/Sales Tax Impact | C19: $M | D19: =IF(D15=0,0,-D15*Assumptions!C22*0.1) -> 0 | E19: =IF(E15=0,0,-E15*Assumptions!C22*0.1) -> 0 | F19: =IF(F15=0,0,-F15*Assumptions!C22*0.1) -> -0.13340952 | G19: =IF(G15=0,0,-G15*Assumptions!C22*0.1) -> -0.2671225 | H19: =IF(H15=0,0,-H15*Assumptions!C22*0.1) -> -0.34115918 | I19: =IF(I15=0,0,-I15*Assumptions!C22*0.1) -> -0.34192683 | J19: =IF(J15=0,0,-J15*Assumptions!C22*0.1) -> -0.34288285 | K19: =IF(K15=0,0,-K15*Assumptions!C22*0.1) -> -0.34402606 | L19: =IF(L15=0,0,-L15*Assumptions!C22*0.1) -> -0.3453554 | M19: =IF(M15=0,0,-M15*Assumptions!C22*0.1) -> -0.34686994 | N19: =IF(N15=0,0,-N15*Assumptions!C22*0.1) -> -0.34856884 | O19: =IF(O15=0,0,-O15*Assumptions!C22*0.1) -> -0.35045139 | P19: =IF(P15=0,0,-P15*Assumptions!C22*0.1) -> -0.35251699 | Q19: =IF(Q15=0,0,-Q15*Assumptions!C22*0.1) -> -0.35476514 | R19: =IF(R15=0,0,-R15*Assumptions!C22*0.1) -> -0.35719545 | S19: =IF(S15=0,0,-S15*Assumptions!C22*0.1) -> -0.35980766 | T19: =IF(T15=0,0,-T15*Assumptions!C22*0.1) -> -0.36260159 | U19: =IF(U15=0,0,-U15*Assumptions!C22*0.1) -> -0.36557718 | V19: =IF(V15=0,0,-V15*Assumptions!C22*0.1) -> -0.36873446 | W19: =IF(W15=0,0,-W15*Assumptions!C22*0.1) -> -0.37207359
B20: FX Translation Gain/(Loss) | C20: $M | D20: =IF(D15=0,0,-D15*Assumptions!C18/(1+Assumptions!C18)) -> 0 | E20: =IF(E15=0,0,-E15*Assumptions!C18/(1+Assumptions!C18)) -> 0 | F20: =IF(F15=0,0,-F15*Assumptions!C18/(1+Assumptions!C18)) -> -0.39705215 | G20: =IF(G15=0,0,-G15*Assumptions!C18/(1+Assumptions!C18)) -> -0.79500745 | H20: =IF(H15=0,0,-H15*Assumptions!C18/(1+Assumptions!C18)) -> -1.0153547 | I20: =IF(I15=0,0,-I15*Assumptions!C18/(1+Assumptions!C18)) -> -1.0176394 | J20: =IF(J15=0,0,-J15*Assumptions!C18/(1+Assumptions!C18)) -> -1.0204847 | K20: =IF(K15=0,0,-K15*Assumptions!C18/(1+Assumptions!C18)) -> -1.0238871 | L20: =IF(L15=0,0,-L15*Assumptions!C18/(1+Assumptions!C18)) -> -1.0278435 | M20: =IF(M15=0,0,-M15*Assumptions!C18/(1+Assumptions!C18)) -> -1.032351 | N20: =IF(N15=0,0,-N15*Assumptions!C18/(1+Assumptions!C18)) -> -1.0374073 | O20: =IF(O15=0,0,-O15*Assumptions!C18/(1+Assumptions!C18)) -> -1.0430101 | P20: =IF(P15=0,0,-P15*Assumptions!C18/(1+Assumptions!C18)) -> -1.0491577 | Q20: =IF(Q15=0,0,-Q15*Assumptions!C18/(1+Assumptions!C18)) -> -1.0558486 | R20: =IF(R15=0,0,-R15*Assumptions!C18/(1+Assumptions!C18)) -> -1.0630817 | S20: =IF(S15=0,0,-S15*Assumptions!C18/(1+Assumptions!C18)) -> -1.0708561 | T20: =IF(T15=0,0,-T15*Assumptions!C18/(1+Assumptions!C18)) -> -1.0791714 | U20: =IF(U15=0,0,-U15*Assumptions!C18/(1+Assumptions!C18)) -> -1.0880273 | V20: =IF(V15=0,0,-V15*Assumptions!C18/(1+Assumptions!C18)) -> -1.097424 | W20: =IF(W15=0,0,-W15*Assumptions!C18/(1+Assumptions!C18)) -> -1.1073619
B21: Net Revenue ($M, USD) | C21: $M | D21: =D15+D18+D19+D20 -> 0 | E21: =E15+E18+E19+E20 -> 0 | F21: =F15+F18+F19+F20 -> 6.973824 | G21: =G15+G18+G19+G20 -> 13.963511 | H21: =H15+H18+H19+H20 -> 17.83369 | I21: =I15+I18+I19+I20 -> 17.873818 | J21: =J15+J18+J19+J20 -> 17.923793 | K21: =K15+K18+K19+K20 -> 17.983553 | ... W21: =W15+W18+W19+W20 -> 19.449704

Sheet CAPEX Schedule
B1: CAPITAL EXPENDITURE SCHEDULE
B3: CAPEX Component | C3: Total ($M) | D3: Yr 1 | E3: Yr 2 | F3: Yr 3 | G3: Yr 4 | H3: Yr 5 | I3: % of Total
B4: HARD COSTS
B5: Land Acquisition & Site Preparation | C5: =SUM(D5:H5) -> 3 | D5: 1 | E5: 1.5 | F5: 0.5 | G5: 0 | H5: 0
B6: Civil Works & Earthworks | C6: =SUM(D6:H6) -> 6 | D6: 2 | E6: 3 | F6: 1 | G6: 0 | H6: 0
B7: Structural/Building Construction | C7: =SUM(D7:H7) -> 6.5 | D7: 0.5 | E7: 2 | F7: 3 | G7: 1 | H7: 0
B8: Equipment & Machinery (imported) | C8: =SUM(D8:H8) -> 10 | D8: 0 | E8: 3 | F8: 5 | G8: 2 | H8: 0
B9: Equipment & Machinery (local) | C9: =SUM(D9:H9) -> 5 | D9: 0 | E9: 1 | F9: 2 | G9: 1.5 | H9: 0.5
B10: Installation & Commissioning | C10: =SUM(D10:H10) -> 6 | D10: 0 | E10: 0 | F10: 2 | G10: 3 | H10: 1
B11: Utility Connections (power, water) | C11: =SUM(D11:H11) -> 2 | D11: 0.5 | E11: 0.5 | F11: 0.5 | G11: 0.5 | H11: 0
B12: Total Hard Costs | C12: =SUM(C5:C11) -> 38.5 | D12: =SUM(D5:D11) -> 4 | E12: =SUM(E5:E11) -> 11 | F12: =SUM(F5:F11) -> 14 | G12: =SUM(G5:G11) -> 8 | H12: =SUM(H5:H11) -> 1.5
D13: 0 | E13: 0 | F13: 0 | G13: 0 | H13: 0
B14: SOFT COSTS
B15: Engineering & Design (FEED/EPC) | C15: =SUM(D15:H15) -> 2.5 | D15: 0.8 | E15: 1.2 | F15: 0.5 | G15: 0 | H15: 0
B16: Environmental & Social Impact Assessment | C16: =SUM(D16:H16) -> 0.5 | D16: 0.3 | E16: 0.2 | F16: 0 | G16: 0 | H16: 0
B17: Legal & Regulatory (permits, licenses) | C17: =SUM(D17:H17) -> 0.9 | D17: 0.2 | E17: 0.3 | F17: 0.2 | G17: 0.1 | H17: 0.1
B18: Insurance (construction period) | C18: =SUM(D18:H18) -> 0.8 | D18: 0.1 | E18: 0.2 | F18: 0.2 | G18: 0.2 | H18: 0.1
B19: Project Management & Owner's Engineer | C19: =SUM(D19:H19) -> 1.8 | D19: 0.3 | E19: 0.5 | F19: 0.5 | G19: 0.3 | H19: 0.2
B20: Interest During Construction (IDC) | C20: =SUM(D20:H20) -> 1.4 | D20: 0 | E20: 0.3 | F20: 0.5 | G20: 0.4 | H20: 0.2
B21: Total Soft Costs | C21: =SUM(C15:C20) -> 7.9 | D21: =SUM(D15:D20) -> 1.7 | E21: =SUM(E15:E20) -> 2.7 | F21: =SUM(F15:F20) -> 1.9 | G21: =SUM(G15:G20) -> 1 | H21: =SUM(H15:H20) -> 0.6
D22: 0 | E22: 0 | F22: 0 | G22: 0 | H22: 0
B23: CONTINGENCY & RESERVES
B24: Physical Contingency | C24: =(C12+C21)*Assumptions!C42 -> 4.64 | D24: 0 | E24: 0 | F24: 0 | G24: 0 | H24: 0
B25: Price Contingency (inflation) | C25: =(C12+C21)*Assumptions!C39*2 -> 3.712 | D25: 0 | E25: 0 | F25: 0 | G25: 0 | H25: 0
B26: FX Contingency | C26: =(C12+C21)*Assumptions!C18 -> 2.32 | D26: 0 | E26: 0 | F26: 0 | G26: 0 | H26: 0
B27: Total Contingency | C27: =SUM(C24:C26) -> 10.672
D28: 0 | E28: 0 | F28: 0 | G28: 0 | H28: 0
B29: TOTAL PROJECT CAPEX | C29: =C12+C21+C27 -> 57.072 | D29: 0 | E29: 0 | F29: 0 | G29: 0 | H29: 0

Sheet OPEX Schedule
B1: OPERATING EXPENDITURE SCHEDULE
B3: OPEX Component | C3: Unit | D3: 1 | E3: 2 | F3: 3 | G3: 4 | H3: 5 | I3: 6 | J3: 7 | K3: 8 | L3: 9 | M3: 10 | N3: 11 | O3: 12 | P3: 13 | Q3: 14 | R3: 15 | S3: 16 | T3: 17 | U3: 18 | V3: 19 | W3: 20
B4: FIXED OPERATING COSTS
B5: Staff & Labor (local) | C5: $M | D5: =IF(1<=(Assumptions!C31/12),0,'CAPEX Schedule'!C29*0.015*(1+Assumptions!C39)^MAX(0,1-(Assumptions!C31/12))) -> 0 | E5: =IF(2<=(Assumptions!C31/12),0,'CAPEX Schedule'!C29*0.015*(1+Assumptions!C39)^MAX(0,2-(Assumptions!C31/12))) -> 0 | F5: =IF(3<=(Assumptions!C31/12),0,'CAPEX Schedule'!C29*0.015*(1+Assumptions!C39)^MAX(0,3-(Assumptions!C31/12))) -> 0.8903232 | G5: =IF(4<=(Assumptions!C31/12),0,'CAPEX Schedule'!C29*0.015*(1+Assumptions!C39)^MAX(0,4-(Assumptions!C31/12))) -> 0.92593613 | H5: =IF(5<=(Assumptions!C31/12),0,'CAPEX Schedule'!C29*0.015*(1+Assumptions!C39)^MAX(0,5-(Assumptions!C31/12))) -> 0.96297357 | I5: =IF(6<=(Assumptions!C31/12),0,'CAPEX Schedule'!C29*0.015*(1+Assumptions!C39)^MAX(0,6-(Assumptions!C31/12))) -> 1.0014925 | J5: =IF(7<=(Assumptions!C31/12),0,'CAPEX Schedule'!C29*0.015*(1+Assumptions!C39)^MAX(0,7-(Assumptions!C31/12))) -> 1.0415522 | K5: =IF(8<=(Assumptions!C31/12),0,'CAPEX Schedule'!C29*0.015*(1+Assumptions!C39)^MAX(0,8-(Assumptions!C31/12))) -> 1.0832143 | L5: =IF(9<=(Assumptions!C31/12),0,'CAPEX Schedule'!C29*0.015*(1+Assumptions!C39)^MAX(0,9-(Assumptions!C31/12))) -> 1.1265429 | M5: =IF(10<=(Assumptions!C31/12),0,'CAPEX Schedule'!C29*0.015*(1+Assumptions!C39)^MAX(0,10-(Assumptions!C31/12))) -> 1.1716046 | N5: =IF(11<=(Assumptions!C31/12),0,'CAPEX Schedule'!C29*0.015*(1+Assumptions!C39)^MAX(0,11-(Assumptions!C31/12))) -> 1.2184688 | O5: =IF(12<=(Assumptions!C31/12),0,'CAPEX Schedule'!C29*0.015*(1+Assumptions!C39)^MAX(0,12-(Assumptions!C31/12))) -> 1.2672075 | P5: =IF(13<=(Assumptions!C31/12),0,'CAPEX Schedule'!C29*0.015*(1+Assumptions!C39)^MAX(0,13-(Assumptions!C31/12))) -> 1.3178958 | Q5: =IF(14<=(Assumptions!C31/12),0,'CAPEX Schedule'!C29*0.015*(1+Assumptions!C39)^MAX(0,14-(Assumptions!C31/12))) -> 1.3706117 | R5: =IF(15<=(Assumptions!C31/12),0,'CAPEX Schedule'!C29*0.015*(1+Assumptions!C39)^MAX(0,15-(Assumptions!C31/12))) -> 1.4254361 | S5: =IF(16<=(Assumptions!C31/12),0,'CAPEX Schedule'!C29*0.015*(1+Assumptions!C39)^MAX(0,16-(Assumptions!C31/12))) -> 1.4824536 | T5: =IF(17<=(Assumptions!C31/12),0,'CAPEX Schedule'!C29*0.015*(1+Assumptions!C39)^MAX(0,17-(Assumptions!C31/12))) -> 1.5417517 | U5: =IF(18<=(Assumptions!C31/12),0,'CAPEX Schedule'!C29*0.015*(1+Assumptions!C39)^MAX(0,18-(Assumptions!C31/12))) -> 1.6034218 | V5: =IF(19<=(Assumptions!C31/12),0,'CAPEX Schedule'!C29*0.015*(1+Assumptions!C39)^MAX(0,19-(Assumptions!C31/12))) -> 1.6675587 | W5: =IF(20<=(Assumptions!C31/12),0,'CAPEX Schedule'!C29*0.015*(1+Assumptions!C39)^MAX(0,20-(Assumptions!C31/12))) -> 1.734261
B6: Staff & Labor (expatriate) | C6: $M | D6: =IF(1<=(Assumptions!C31/12),0,'CAPEX Schedule'!C29*0.008*(1+Assumptions!C39)^MAX(0,1-(Assumptions!C31/12))) -> 0 | E6: =IF(2<=(Assumptions!C31/12),0,'CAPEX Schedule'!C29*0.008*(1+Assumptions!C39)^MAX(0,2-(Assumptions!C31/12))) -> 0 | F6: =IF(3<=(Assumptions!C31/12),0,'CAPEX Schedule'!C29*0.008*(1+Assumptions!C39)^MAX(0,3-(Assumptions!C31/12))) -> 0.47483904 | G6: =IF(4<=(Assumptions!C31/12),0,'CAPEX Schedule'!C29*0.008*(1+Assumptions!C39)^MAX(0,4-(Assumptions!C31/12))) -> 0.4938326 | H6: =IF(5<=(Assumptions!C31/12),0,'CAPEX Schedule'!C29*0.008*(1+Assumptions!C39)^MAX(0,5-(Assumptions!C31/12))) -> 0.51358591 | I6: =IF(6<=(Assumptions!C31/12),0,'CAPEX Schedule'!C29*0.008*(1+Assumptions!C39)^MAX(0,6-(Assumptions!C31/12))) -> 0.53412934 | J6: =IF(7<=(Assumptions!C31/12),0,'CAPEX Schedule'!C29*0.008*(1+Assumptions!C39)^MAX(0,7-(Assumptions!C31/12))) -> 0.55549452 | K6: =IF(8<=(Assumptions!C31/12),0,'CAPEX Schedule'!C29*0.008*(1+Assumptions!C39)^MAX(0,8-(Assumptions!C31/12))) -> 0.5777143 | L6: =IF(9<=(Assumptions!C31/12),0,'CAPEX Schedule'!C29*0.008*(1+Assumptions!C39)^MAX(0,9-(Assumptions!C31/12))) -> 0.60082287 | M6: =IF(10<=(Assumptions!C31/12),0,'CAPEX Schedule'!C29*0.008*(1+Assumptions!C39)^MAX(0,10-(Assumptions!C31/12))) -> 0.62485578 | N6: =IF(11<=(Assumptions!C31/12),0,'CAPEX Schedule'!C29*0.008*(1+Assumptions!C39)^MAX(0,11-(Assumptions!C31/12))) -> 0.64985001 | O6: =IF(12<=(Assumptions!C31/12),0,'CAPEX Schedule'!C29*0.008*(1+Assumptions!C39)^MAX(0,12-(Assumptions!C31/12))) -> 0.67584401 | P6: =IF(13<=(Assumptions!C31/12),0,'CAPEX Schedule'!C29*0.008*(1+Assumptions!C39)^MAX(0,13-(Assumptions!C31/12))) -> 0.70287778 | Q6: =IF(14<=(Assumptions!C31/12),0,'CAPEX Schedule'!C29*0.008*(1+Assumptions!C39)^MAX(0,14-(Assumptions!C31/12))) -> 0.73099289 | R6: =IF(15<=(Assumptions!C31/12),0,'CAPEX Schedule'!C29*0.008*(1+Assumptions!C39)^MAX(0,15-(Assumptions!C31/12))) -> 0.7602326 | S6: =IF(16<=(Assumptions!C31/12),0,'CAPEX Schedule'!C29*0.008*(1+Assumptions!C39)^MAX(0,16-(Assumptions!C31/12))) -> 0.79064191 | T6: =IF(17<=(Assumptions!C31/12),0,'CAPEX Schedule'!C29*0.008*(1+Assumptions!C39)^MAX(0,17-(Assumptions!C31/12))) -> 0.82226758 | U6: =IF(18<=(Assumptions!C31/12),0,'CAPEX Schedule'!C29*0.008*(1+Assumptions!C39)^MAX(0,18-(Assumptions!C31/12))) -> 0.85515829 | V6: =IF(19<=(Assumptions!C31/12),0,'CAPEX Schedule'!C29*0.008*(1+Assumptions!C39)^MAX(0,19-(Assumptions!C31/12))) -> 0.88936462 | W6: =IF(20<=(Assumptions!C31/12),0,'CAPEX Schedule'!C29*0.008*(1+Assumptions!C39)^MAX(0,20-(Assumptions!C31/12))) -> 0.9249392
B7: Insurance (operational) | C7: $M | D7: =IF(1<=(Assumptions!C31/12),0,'CAPEX Schedule'!C29*0.004*(1+Assumptions!C39)^MAX(0,1-(Assumptions!C31/12))) -> 0 | E7: =IF(2<=(Assumptions!C31/12),0,'CAPEX Schedule'!C29*0.004*(1+Assumptions!C39)^MAX(0,2-(Assumptions!C31/12))) -> 0 | F7: =IF(3<=(Assumptions!C31/12),0,'CAPEX Schedule'!C29*0.004*(1+Assumptions!C39)^MAX(0,3-(Assumptions!C31/12))) -> 0.23741952 | G7: =IF(4<=(Assumptions!C31/12),0,'CAPEX Schedule'!C29*0.004*(1+Assumptions!C39)^MAX(0,4-(Assumptions!C31/12))) -> 0.2469163 | H7: =IF(5<=(Assumptions!C31/12),0,'CAPEX Schedule'!C29*0.004*(1+Assumptions!C39)^MAX(0,5-(Assumptions!C31/12))) -> 0.25679295 | I7: =IF(6<=(Assumptions!C31/12),0,'CAPEX Schedule'!C29*0.004*(1+Assumptions!C39)^MAX(0,6-(Assumptions!C31/12))) -> 0.26706467 | J7: =IF(7<=(Assumptions!C31/12),0,'CAPEX Schedule'!C29*0.004*(1+Assumptions!C39)^MAX(0,7-(Assumptions!C31/12))) -> 0.27774726 | K7: =IF(8<=(Assumptions!C31/12),0,'CAPEX Schedule'!C29*0.004*(1+Assumptions!C39)^MAX(0,8-(Assumptions!C31/12))) -> 0.28885715 | L7: =IF(9<=(Assumptions!C31/12),0,'CAPEX Schedule'!C29*0.004*(1+Assumptions!C39)^MAX(0,9-(Assumptions!C31/12))) -> 0.30041143 | M7: =IF(10<=(Assumptions!C31/12),0,'CAPEX Schedule'!C29*0.004*(1+Assumptions!C39)^MAX(0,10-(Assumptions!C31/12))) -> 0.31242789 | N7: =IF(11<=(Assumptions!C31/12),0,'CAPEX Schedule'!C29*0.004*(1+Assumptions!C39)^MAX(0,11-(Assumptions!C31/12))) -> 0.32492501 | O7: =IF(12<=(Assumptions!C31/12),0,'CAPEX Schedule'!C29*0.004*(1+Assumptions!C39)^MAX(0,12-(Assumptions!C31/12))) -> 0.33792201 | P7: =IF(13<=(Assumptions!C31/12),0,'CAPEX Schedule'!C29*0.004*(1+Assumptions!C39)^MAX(0,13-(Assumptions!C31/12))) -> 0.35143889 | Q7: =IF(14<=(Assumptions!C31/12),0,'CAPEX Schedule'!C29*0.004*(1+Assumptions!C39)^MAX(0,14-(Assumptions!C31/12))) -> 0.36549644 | R7: =IF(15<=(Assumptions!C31/12),0,'CAPEX Schedule'!C29*0.004*(1+Assumptions!C39)^MAX(0,15-(Assumptions!C31/12))) -> 0.3801163 | S7: =IF(16<=(Assumptions!C31/12),0,'CAPEX Schedule'!C29*0.004*(1+Assumptions!C39)^MAX(0,16-(Assumptions!C31/12))) -> 0.39532095 | T7: =IF(17<=(Assumptions!C31/12),0,'CAPEX Schedule'!C29*0.004*(1+Assumptions!C39)^MAX(0,17-(Assumptions!C31/12))) -> 0.41113379 | U7: =IF(18<=(Assumptions!C31/12),0,'CAPEX Schedule'!C29*0.004*(1+Assumptions!C39)^MAX(0,18-(Assumptions!C31/12))) -> 0.42757914 | V7: =IF(19<=(Assumptions!C31/12),0,'CAPEX Schedule'!C29*0.004*(1+Assumptions!C39)^MAX(0,19-(Assumptions!C31/12))) -> 0.44468231 | W7: =IF(20<=(Assumptions!C31/12),0,'CAPEX Schedule'!C29*0.004*(1+Assumptions!C39)^MAX(0,20-(Assumptions!C31/12))) -> 0.4624696
B8: Land Lease / Concession Fee | C8: $M | D8: =IF(1<=(Assumptions!C31/12),0,'CAPEX Schedule'!C29*0.002*(1+Assumptions!C39)^MAX(0,1-(Assumptions!C31/12))) -> 0 | E8: =IF(2<=(Assumptions!C31/12),0,'CAPEX Schedule'!C29*0.002*(1+Assumptions!C39)^MAX(0,2-(Assumptions!C31/12))) -> 0 | F8: =IF(3<=(Assumptions!C31/12),0,'CAPEX Schedule'!C29*0.002*(1+Assumptions!C39)^MAX(0,3-(Assumptions!C31/12))) -> 0.11870976 | G8: =IF(4<=(Assumptions!C31/12),0,'CAPEX Schedule'!C29*0.002*(1+Assumptions!C39)^MAX(0,4-(Assumptions!C31/12))) -> 0.12345815 | H8: =IF(5<=(Assumptions!C31/12),0,'CAPEX Schedule'!C29*0.002*(1+Assumptions!C39)^MAX(0,5-(Assumptions!C31/12))) -> 0.12839648 | I8: =IF(6<=(Assumptions!C31/12),0,'CAPEX Schedule'!C29*0.002*(1+Assumptions!C39)^MAX(0,6-(Assumptions!C31/12))) -> 0.13353234 | J8: =IF(7<=(Assumptions!C31/12),0,'CAPEX Schedule'!C29*0.002*(1+Assumptions!C39)^MAX(0,7-(Assumptions!C31/12))) -> 0.13887363 | K8: =IF(8<=(Assumptions!C31/12),0,'CAPEX Schedule'!C29*0.002*(1+Assumptions!C39)^MAX(0,8-(Assumptions!C31/12))) -> 0.14442857 | L8: =IF(9<=(Assumptions!C31/12),0,'CAPEX Schedule'!C29*0.002*(1+Assumptions!C39)^MAX(0,9-(Assumptions!C31/12))) -> 0.15020572 | M8: =IF(10<=(Assumptions!C31/12),0,'CAPEX Schedule'!C29*0.002*(1+Assumptions!C39)^MAX(0,10-(Assumptions!C31/12))) -> 0.15621395 | N8: =IF(11<=(Assumptions!C31/12),0,'CAPEX Schedule'!C29*0.002*(1+Assumptions!C39)^MAX(0,11-(Assumptions!C31/12))) -> 0.1624625 | O8: =IF(12<=(Assumptions!C31/12),0,'CAPEX Schedule'!C29*0.002*(1+Assumptions!C39)^MAX(0,12-(Assumptions!C31/12))) -> 0.168961 | P8: =IF(13<=(Assumptions!C31/12),0,'CAPEX Schedule'!C29*0.002*(1+Assumptions!C39)^MAX(0,13-(Assumptions!C31/12))) -> 0.17571944 | Q8: =IF(14<=(Assumptions!C31/12),0,'CAPEX Schedule'!C29*0.002*(1+Assumptions!C39)^MAX(0,14-(Assumptions!C31/12))) -> 0.18274822 | R8: =IF(15<=(Assumptions!C31/12),0,'CAPEX Schedule'!C29*0.002*(1+Assumptions!C39)^MAX(0,15-(Assumptions!C31/12))) -> 0.19005815 | S8: =IF(16<=(Assumptions!C31/12),0,'CAPEX Schedule'!C29*0.002*(1+Assumptions!C39)^MAX(0,16-(Assumptions!C31/12))) -> 0.19766048 | T8: =IF(17<=(Assumptions!C31/12),0,'CAPEX Schedule'!C29*0.002*(1+Assumptions!C39)^MAX(0,17-(Assumptions!C31/12))) -> 0.2055669 | U8: =IF(18<=(Assumptions!C31/12),0,'CAPEX Schedule'!C29*0.002*(1+Assumptions!C39)^MAX(0,18-(Assumptions!C31/12))) -> 0.21378957 | V8: =IF(19<=(Assumptions!C31/12),0,'CAPEX Schedule'!C29*0.002*(1+Assumptions!C39)^MAX(0,19-(Assumptions!C31/12))) -> 0.22234115 | W8: =IF(20<=(Assumptions!C31/12),0,'CAPEX Schedule'!C29*0.002*(1+Assumptions!C39)^MAX(0,20-(Assumptions!C31/12))) -> 0.2312348
B9: Security & Community Relations | C9: $M | D9: =IF(1<=(Assumptions!C31/12),0,'CAPEX Schedule'!C29*0.0015*(1+Assumptions!C39)^MAX(0,1-(Assumptions!C31/12))) -> 0 | E9: =IF(2<=(Assumptions!C31/12),0,'CAPEX Schedule'!C29*0.0015*(1+Assumptions!C39)^MAX(0,2-(Assumptions!C31/12))) -> 0 | F9: =IF(3<=(Assumptions!C31/12),0,'CAPEX Schedule'!C29*0.0015*(1+Assumptions!C39)^MAX(0,3-(Assumptions!C31/12))) -> 0.08903232 | G9: =IF(4<=(Assumptions!C31/12),0,'CAPEX Schedule'!C29*0.0015*(1+Assumptions!C39)^MAX(0,4-(Assumptions!C31/12))) -> 0.092593613 | H9: =IF(5<=(Assumptions!C31/12),0,'CAPEX Schedule'!C29*0.0015*(1+Assumptions!C39)^MAX(0,5-(Assumptions!C31/12))) -> 0.096297357 | I9: =IF(6<=(Assumptions!C31/12),0,'CAPEX Schedule'!C29*0.0015*(1+Assumptions!C39)^MAX(0,6-(Assumptions!C31/12))) -> 0.10014925 | J9: =IF(7<=(Assumptions!C31/12),0,'CAPEX Schedule'!C29*0.0015*(1+Assumptions!C39)^MAX(0,7-(Assumptions!C31/12))) -> 0.10415522 | K9: =IF(8<=(Assumptions!C31/12),0,'CAPEX Schedule'!C29*0.0015*(1+Assumptions!C39)^MAX(0,8-(Assumptions!C31/12))) -> 0.10832143 | L9: =IF(9<=(Assumptions!C31/12),0,'CAPEX Schedule'!C29*0.0015*(1+Assumptions!C39)^MAX(0,9-(Assumptions!C31/12))) -> 0.11265429 | M9: =IF(10<=(Assumptions!C31/12),0,'CAPEX Schedule'!C29*0.0015*(1+Assumptions!C39)^MAX(0,10-(Assumptions!C31/12))) -> 0.11716046 | N9: =IF(11<=(Assumptions!C31/12),0,'CAPEX Schedule'!C29*0.0015*(1+Assumptions!C39)^MAX(0,11-(Assumptions!C31/12))) -> 0.12184688 | O9: =IF(12<=(Assumptions!C31/12),0,'CAPEX Schedule'!C29*0.0015*(1+Assumptions!C39)^MAX(0,12-(Assumptions!C31/12))) -> 0.12672075 | P9: =IF(13<=(Assumptions!C31/12),0,'CAPEX Schedule'!C29*0.0015*(1+Assumptions!C39)^MAX(0,13-(Assumptions!C31/12))) -> 0.13178958 | Q9: =IF(14<=(Assumptions!C31/12),0,'CAPEX Schedule'!C29*0.0015*(1+Assumptions!C39)^MAX(0,14-(Assumptions!C31/12))) -> 0.13706117 | R9: =IF(15<=(Assumptions!C31/12),0,'CAPEX Schedule'!C29*0.0015*(1+Assumptions!C39)^MAX(0,15-(Assumptions!C31/12))) -> 0.14254361 | S9: =IF(16<=(Assumptions!C31/12),0,'CAPEX Schedule'!C29*0.0015*(1+Assumptions!C39)^MAX(0,16-(Assumptions!C31/12))) -> 0.14824536 | T9: =IF(17<=(Assumptions!C31/12),0,'CAPEX Schedule'!C29*0.0015*(1+Assumptions!C39)^MAX(0,17-(Assumptions!C31/12))) -> 0.15417517 | U9: =IF(18<=(Assumptions!C31/12),0,'CAPEX Schedule'!C29*0.0015*(1+Assumptions!C39)^MAX(0,18-(Assumptions!C31/12))) -> 0.16034218 | V9: =IF(19<=(Assumptions!C31/12),0,'CAPEX Schedule'!C29*0.0015*(1+Assumptions!C39)^MAX(0,19-(Assumptions!C31/12))) -> 0.16675587 | W9: =IF(20<=(Assumptions!C31/12),0,'CAPEX Schedule'!C29*0.0015*(1+Assumptions!C39)^MAX(0,20-(Assumptions!C31/12))) -> 0.1734261
B10: Total Fixed OPEX | C10: $M | D10: =SUM(D5:D9) -> 0 | E10: =SUM(E5:E9) -> 0 | F10: =SUM(F5:F9) -> 1.8103238 | G10: =SUM(G5:G9) -> 1.8827368 | H10: =SUM(H5:H9) -> 1.9580463 | I10: =SUM(I5:I9) -> 2.0363681 | J10: =SUM(J5:J9) -> 2.1178228 | K10: =SUM(K5:K9) -> 2.2025358 | ... W10: =SUM(W5:W9) -> 3.5263307
B12: VARIABLE OPERATING COSTS
B13: Raw Materials / Consumables | C13: $M | D13: =IF(1<=(Assumptions!C31/12),0,'Revenue Build'!D15*0.06*(1+Assumptions!C39)^MAX(0,1-(Assumptions!C31/12))) -> 0 | E13: =IF(2<=(Assumptions!C31/12),0,'Revenue Build'!E15*0.06*(1+Assumptions!C39)^MAX(0,2-(Assumptions!C31/12))) -> 0 | F13: =IF(3<=(Assumptions!C31/12),0,'Revenue Build'!F15*0.06*(1+Assumptions!C39)^MAX(0,3-(Assumptions!C31/12))) -> 0.52029714 | G13: =IF(4<=(Assumptions!C31/12),0,'Revenue Build'!G15*0.06*(1+Assumptions!C39)^MAX(0,4-(Assumptions!C31/12))) -> 1.0834489 | H13: =IF(5<=(Assumptions!C31/12),0,'Revenue Build'!H15*0.06*(1+Assumptions!C39)^MAX(0,5-(Assumptions!C31/12))) -> 1.4390913 | I13: =IF(6<=(Assumptions!C31/12),0,'Revenue Build'!I15*0.06*(1+Assumptions!C39)^MAX(0,6-(Assumptions!C31/12))) -> 1.5000226 | J13: =IF(7<=(Assumptions!C31/12),0,'Revenue Build'!J15*0.06*(1+Assumptions!C39)^MAX(0,7-(Assumptions!C31/12))) -> 1.5643853 | K13: =IF(8<=(Assumptions!C31/12),0,'Revenue Build'!K15*0.06*(1+Assumptions!C39)^MAX(0,8-(Assumptions!C31/12))) -> 1.6323852 | L13: =IF(9<=(Assumptions!C31/12),0,'Revenue Build'!L15*0.06*(1+Assumptions!C39)^MAX(0,9-(Assumptions!C31/12))) -> 1.7042406 | M13: =IF(10<=(Assumptions!C31/12),0,'Revenue Build'!M15*0.06*(1+Assumptions!C39)^MAX(0,10-(Assumptions!C31/12))) -> 1.780183 | N13: =IF(11<=(Assumptions!C31/12),0,'Revenue Build'!N15*0.06*(1+Assumptions!C39)^MAX(0,11-(Assumptions!C31/12))) -> 1.8604581 | O13: =IF(12<=(Assumptions!C31/12),0,'Revenue Build'!O15*0.06*(1+Assumptions!C39)^MAX(0,12-(Assumptions!C31/12))) -> 1.9453263 | P13: =IF(13<=(Assumptions!C31/12),0,'Revenue Build'!P15*0.06*(1+Assumptions!C39)^MAX(0,13-(Assumptions!C31/12))) -> 2.0350639 | Q13: =IF(14<=(Assumptions!C31/12),0,'Revenue Build'!Q15*0.06*(1+Assumptions!C39)^MAX(0,14-(Assumptions!C31/12))) -> 2.129964 | R13: =IF(15<=(Assumptions!C31/12),0,'Revenue Build'!R15*0.06*(1+Assumptions!C39)^MAX(0,15-(Assumptions!C31/12))) -> 2.2303376 | S13: =IF(16<=(Assumptions!C31/12),0,'Revenue Build'!S15*0.06*(1+Assumptions!C39)^MAX(0,16-(Assumptions!C31/12))) -> 2.3365142 | T13: =IF(17<=(Assumptions!C31/12),0,'Revenue Build'!T15*0.06*(1+Assumptions!C39)^MAX(0,17-(Assumptions!C31/12))) -> 2.4488437 | U13: =IF(18<=(Assumptions!C31/12),0,'Revenue Build'!U15*0.06*(1+Assumptions!C39)^MAX(0,18-(Assumptions!C31/12))) -> 2.567697 | V13: =IF(19<=(Assumptions!C31/12),0,'Revenue Build'!V15*0.06*(1+Assumptions!C39)^MAX(0,19-(Assumptions!C31/12))) -> 2.6934677 | W13: =IF(20<=(Assumptions!C31/12),0,'Revenue Build'!W15*0.06*(1+Assumptions!C39)^MAX(0,20-(Assumptions!C31/12))) -> 2.8265731
B14: Energy / Fuel Costs | C14: $M | D14: =IF(1<=(Assumptions!C31/12),0,'Revenue Build'!D15*0.04*(1+Assumptions!C39)^MAX(0,1-(Assumptions!C31/12))) -> 0 | E14: =IF(2<=(Assumptions!C31/12),0,'Revenue Build'!E15*0.04*(1+Assumptions!C39)^MAX(0,2-(Assumptions!C31/12))) -> 0 | F14: =IF(3<=(Assumptions!C31/12),0,'Revenue Build'!F15*0.04*(1+Assumptions!C39)^MAX(0,3-(Assumptions!C31/12))) -> 0.34686476 | G14: =IF(4<=(Assumptions!C31/12),0,'Revenue Build'!G15*0.04*(1+Assumptions!C39)^MAX(0,4-(Assumptions!C31/12))) -> 0.72229925 | H14: =IF(5<=(Assumptions!C31/12),0,'Revenue Build'!H15*0.04*(1+Assumptions!C39)^MAX(0,5-(Assumptions!C31/12))) -> 0.9593942 | I14: =IF(6<=(Assumptions!C31/12),0,'Revenue Build'!I15*0.04*(1+Assumptions!C39)^MAX(0,6-(Assumptions!C31/12))) -> 1.0000151 | J14: =IF(7<=(Assumptions!C31/12),0,'Revenue Build'!J15*0.04*(1+Assumptions!C39)^MAX(0,7-(Assumptions!C31/12))) -> 1.0429235 | K14: =IF(8<=(Assumptions!C31/12),0,'Revenue Build'!K15*0.04*(1+Assumptions!C39)^MAX(0,8-(Assumptions!C31/12))) -> 1.0882568 | L14: =IF(9<=(Assumptions!C31/12),0,'Revenue Build'!L15*0.04*(1+Assumptions!C39)^MAX(0,9-(Assumptions!C31/12))) -> 1.1361604 | M14: =IF(10<=(Assumptions!C31/12),0,'Revenue Build'!M15*0.04*(1+Assumptions!C39)^MAX(0,10-(Assumptions!C31/12))) -> 1.1867887 | N14: =IF(11<=(Assumptions!C31/12),0,'Revenue Build'!N15*0.04*(1+Assumptions!C39)^MAX(0,11-(Assumptions!C31/12))) -> 1.2403054 | O14: =IF(12<=(Assumptions!C31/12),0,'Revenue Build'!O15*0.04*(1+Assumptions!C39)^MAX(0,12-(Assumptions!C31/12))) -> 1.2968842 | P14: =IF(13<=(Assumptions!C31/12),0,'Revenue Build'!P15*0.04*(1+Assumptions!C39)^MAX(0,13-(Assumptions!C31/12))) -> 1.3567093 | Q14: =IF(14<=(Assumptions!C31/12),0,'Revenue Build'!Q15*0.04*(1+Assumptions!C39)^MAX(0,14-(Assumptions!C31/12))) -> 1.419976 | R14: =IF(15<=(Assumptions!C31/12),0,'Revenue Build'!R15*0.04*(1+Assumptions!C39)^MAX(0,15-(Assumptions!C31/12))) -> 1.4868917 | S14: =IF(16<=(Assumptions!C31/12),0,'Revenue Build'!S15*0.04*(1+Assumptions!C39)^MAX(0,16-(Assumptions!C31/12))) -> 1.5576761 | T14: =IF(17<=(Assumptions!C31/12),0,'Revenue Build'!T15*0.04*(1+Assumptions!C39)^MAX(0,17-(Assumptions!C31/12))) -> 1.6325625 | U14: =IF(18<=(Assumptions!C31/12),0,'Revenue Build'!U15*0.04*(1+Assumptions!C39)^MAX(0,18-(Assumptions!C31/12))) -> 1.711798 | V14: =IF(19<=(Assumptions!C31/12),0,'Revenue Build'!V15*0.04*(1+Assumptions!C39)^MAX(0,19-(Assumptions!C31/12))) -> 1.7956451 | W14: =IF(20<=(Assumptions!C31/12),0,'Revenue Build'!W15*0.04*(1+Assumptions!C39)^MAX(0,20-(Assumptions!C31/12))) -> 1.884382
B15: Maintenance & Repairs | C15: $M | D15: =IF(1<=(Assumptions!C31/12),0,'CAPEX Schedule'!C29*Assumptions!C40*(1+Assumptions!C39)^MAX(0,1-(Assumptions!C31/12))) -> 0 | E15: =IF(2<=(Assumptions!C31/12),0,'CAPEX Schedule'!C29*Assumptions!C40*(1+Assumptions!C39)^MAX(0,2-(Assumptions!C31/12))) -> 0 | F15: =IF(3<=(Assumptions!C31/12),0,'CAPEX Schedule'!C29*Assumptions!C40*(1+Assumptions!C39)^MAX(0,3-(Assumptions!C31/12))) -> 1.1870976 | G15: =IF(4<=(Assumptions!C31/12),0,'CAPEX Schedule'!C29*Assumptions!C40*(1+Assumptions!C39)^MAX(0,4-(Assumptions!C31/12))) -> 1.2345815 | H15: =IF(5<=(Assumptions!C31/12),0,'CAPEX Schedule'!C29*Assumptions!C40*(1+Assumptions!C39)^MAX(0,5-(Assumptions!C31/12))) -> 1.2839648 | I15: =IF(6<=(Assumptions!C31/12),0,'CAPEX Schedule'!C29*Assumptions!C40*(1+Assumptions!C39)^MAX(0,6-(Assumptions!C31/12))) -> 1.3353234 | J15: =IF(7<=(Assumptions!C31/12),0,'CAPEX Schedule'!C29*Assumptions!C40*(1+Assumptions!C39)^MAX(0,7-(Assumptions!C31/12))) -> 1.3887363 | K15: =IF(8<=(Assumptions!C31/12),0,'CAPEX Schedule'!C29*Assumptions!C40*(1+Assumptions!C39)^MAX(0,8-(Assumptions!C31/12))) -> 1.4442857 | L15: =IF(9<=(Assumptions!C31/12),0,'CAPEX Schedule'!C29*Assumptions!C40*(1+Assumptions!C39)^MAX(0,9-(Assumptions!C31/12))) -> 1.5020572 | M15: =IF(10<=(Assumptions!C31/12),0,'CAPEX Schedule'!C29*Assumptions!C40*(1+Assumptions!C39)^MAX(0,10-(Assumptions!C31/12))) -> 1.5621395 | N15: =IF(11<=(Assumptions!C31/12),0,'CAPEX Schedule'!C29*Assumptions!C40*(1+Assumptions!C39)^MAX(0,11-(Assumptions!C31/12))) -> 1.624625 | O15: =IF(12<=(Assumptions!C31/12),0,'CAPEX Schedule'!C29*Assumptions!C40*(1+Assumptions!C39)^MAX(0,12-(Assumptions!C31/12))) -> 1.68961 | P15: =IF(13<=(Assumptions!C31/12),0,'CAPEX Schedule'!C29*Assumptions!C40*(1+Assumptions!C39)^MAX(0,13-(Assumptions!C31/12))) -> 1.7571944 | Q15: =IF(14<=(Assumptions!C31/12),0,'CAPEX Schedule'!C29*Assumptions!C40*(1+Assumptions!C39)^MAX(0,14-(Assumptions!C31/12))) -> 1.8274822 | R15: =IF(15<=(Assumptions!C31/12),0,'CAPEX Schedule'!C29*Assumptions!C40*(1+Assumptions!C39)^MAX(0,15-(Assumptions!C31/12))) -> 1.9005815 | S15: =IF(16<=(Assumptions!C31/12),0,'CAPEX Schedule'!C29*Assumptions!C40*(1+Assumptions!C39)^MAX(0,16-(Assumptions!C31/12))) -> 1.9766048 | T15: =IF(17<=(Assumptions!C31/12),0,'CAPEX Schedule'!C29*Assumptions!C40*(1+Assumptions!C39)^MAX(0,17-(Assumptions!C31/12))) -> 2.055669 | U15: =IF(18<=(Assumptions!C31/12),0,'CAPEX Schedule'!C29*Assumptions!C40*(1+Assumptions!C39)^MAX(0,18-(Assumptions!C31/12))) -> 2.1378957 | V15: =IF(19<=(Assumptions!C31/12),0,'CAPEX Schedule'!C29*Assumptions!C40*(1+Assumptions!C39)^MAX(0,19-(Assumptions!C31/12))) -> 2.2234115 | W15: =IF(20<=(Assumptions!C31/12),0,'CAPEX Schedule'!C29*Assumptions!C40*(1+Assumptions!C39)^MAX(0,20-(Assumptions!C31/12))) -> 2.312348
B16: Transport & Logistics | C16: $M | D16: =IF(1<=(Assumptions!C31/12),0,'Revenue Build'!D15*0.03*(1+Assumptions!C39)^MAX(0,1-(Assumptions!C31/12))) -> 0 | E16: =IF(2<=(Assumptions!C31/12),0,'Revenue Build'!E15*0.03*(1+Assumptions!C39)^MAX(0,2-(Assumptions!C31/12))) -> 0 | F16: =IF(3<=(Assumptions!C31/12),0,'Revenue Build'!F15*0.03*(1+Assumptions!C39)^MAX(0,3-(Assumptions!C31/12))) -> 0.26014857 | G16: =IF(4<=(Assumptions!C31/12),0,'Revenue Build'!G15*0.03*(1+Assumptions!C39)^MAX(0,4-(Assumptions!C31/12))) -> 0.54172444 | H16: =IF(5<=(Assumptions!C31/12),0,'Revenue Build'!H15*0.03*(1+Assumptions!C39)^MAX(0,5-(Assumptions!C31/12))) -> 0.71954565 | I16: =IF(6<=(Assumptions!C31/12),0,'Revenue Build'!I15*0.03*(1+Assumptions!C39)^MAX(0,6-(Assumptions!C31/12))) -> 0.7500113 | J16: =IF(7<=(Assumptions!C31/12),0,'Revenue Build'!J15*0.03*(1+Assumptions!C39)^MAX(0,7-(Assumptions!C31/12))) -> 0.78219265 | K16: =IF(8<=(Assumptions!C31/12),0,'Revenue Build'!K15*0.03*(1+Assumptions!C39)^MAX(0,8-(Assumptions!C31/12))) -> 0.81619259 | L16: =IF(9<=(Assumptions!C31/12),0,'Revenue Build'!L15*0.03*(1+Assumptions!C39)^MAX(0,9-(Assumptions!C31/12))) -> 0.85212028 | M16: =IF(10<=(Assumptions!C31/12),0,'Revenue Build'!M15*0.03*(1+Assumptions!C39)^MAX(0,10-(Assumptions!C31/12))) -> 0.89009149 | N16: =IF(11<=(Assumptions!C31/12),0,'Revenue Build'!N15*0.03*(1+Assumptions!C39)^MAX(0,11-(Assumptions!C31/12))) -> 0.93022903 | O16: =IF(12<=(Assumptions!C31/12),0,'Revenue Build'!O15*0.03*(1+Assumptions!C39)^MAX(0,12-(Assumptions!C31/12))) -> 0.97266313 | P16: =IF(13<=(Assumptions!C31/12),0,'Revenue Build'!P15*0.03*(1+Assumptions!C39)^MAX(0,13-(Assumptions!C31/12))) -> 1.0175319 | Q16: =IF(14<=(Assumptions!C31/12),0,'Revenue Build'!Q15*0.03*(1+Assumptions!C39)^MAX(0,14-(Assumptions!C31/12))) -> 1.064982 | R16: =IF(15<=(Assumptions!C31/12),0,'Revenue Build'!R15*0.03*(1+Assumptions!C39)^MAX(0,15-(Assumptions!C31/12))) -> 1.1151688 | S16: =IF(16<=(Assumptions!C31/12),0,'Revenue Build'!S15*0.03*(1+Assumptions!C39)^MAX(0,16-(Assumptions!C31/12))) -> 1.1682571 | T16: =IF(17<=(Assumptions!C31/12),0,'Revenue Build'!T15*0.03*(1+Assumptions!C39)^MAX(0,17-(Assumptions!C31/12))) -> 1.2244218 | U16: =IF(18<=(Assumptions!C31/12),0,'Revenue Build'!U15*0.03*(1+Assumptions!C39)^MAX(0,18-(Assumptions!C31/12))) -> 1.2838485 | V16: =IF(19<=(Assumptions!C31/12),0,'Revenue Build'!V15*0.03*(1+Assumptions!C39)^MAX(0,19-(Assumptions!C31/12))) -> 1.3467338 | W16: =IF(20<=(Assumptions!C31/12),0,'Revenue Build'!W15*0.03*(1+Assumptions!C39)^MAX(0,20-(Assumptions!C31/12))) -> 1.4132865
B17: Water & Environmental | C17: $M | D17: =IF(1<=(Assumptions!C31/12),0,'Revenue Build'!D15*0.01*(1+Assumptions!C39)^MAX(0,1-(Assumptions!C31/12))) -> 0 | E17: =IF(2<=(Assumptions!C31/12),0,'Revenue Build'!E15*0.01*(1+Assumptions!C39)^MAX(0,2-(Assumptions!C31/12))) -> 0 | F17: =IF(3<=(Assumptions!C31/12),0,'Revenue Build'!F15*0.01*(1+Assumptions!C39)^MAX(0,3-(Assumptions!C31/12))) -> 0.08671619 | G17: =IF(4<=(Assumptions!C31/12),0,'Revenue Build'!G15*0.01*(1+Assumptions!C39)^MAX(0,4-(Assumptions!C31/12))) -> 0.18057481 | H17: =IF(5<=(Assumptions!C31/12),0,'Revenue Build'!H15*0.01*(1+Assumptions!C39)^MAX(0,5-(Assumptions!C31/12))) -> 0.23984855 | I17: =IF(6<=(Assumptions!C31/12),0,'Revenue Build'!I15*0.01*(1+Assumptions!C39)^MAX(0,6-(Assumptions!C31/12))) -> 0.25000377 | J17: =IF(7<=(Assumptions!C31/12),0,'Revenue Build'!J15*0.01*(1+Assumptions!C39)^MAX(0,7-(Assumptions!C31/12))) -> 0.26073088 | K17: =IF(8<=(Assumptions!C31/12),0,'Revenue Build'!K15*0.01*(1+Assumptions!C39)^MAX(0,8-(Assumptions!C31/12))) -> 0.2720642 | L17: =IF(9<=(Assumptions!C31/12),0,'Revenue Build'!L15*0.01*(1+Assumptions!C39)^MAX(0,9-(Assumptions!C31/12))) -> 0.28404009 | M17: =IF(10<=(Assumptions!C31/12),0,'Revenue Build'!M15*0.01*(1+Assumptions!C39)^MAX(0,10-(Assumptions!C31/12))) -> 0.29669716 | N17: =IF(11<=(Assumptions!C31/12),0,'Revenue Build'!N15*0.01*(1+Assumptions!C39)^MAX(0,11-(Assumptions!C31/12))) -> 0.31007634 | O17: =IF(12<=(Assumptions!C31/12),0,'Revenue Build'!O15*0.01*(1+Assumptions!C39)^MAX(0,12-(Assumptions!C31/12))) -> 0.32422104 | P17: =IF(13<=(Assumptions!C31/12),0,'Revenue Build'!P15*0.01*(1+Assumptions!C39)^MAX(0,13-(Assumptions!C31/12))) -> 0.33917732 | Q17: =IF(14<=(Assumptions!C31/12),0,'Revenue Build'!Q15*0.01*(1+Assumptions!C39)^MAX(0,14-(Assumptions!C31/12))) -> 0.35499401 | R17: =IF(15<=(Assumptions!C31/12),0,'Revenue Build'!R15*0.01*(1+Assumptions!C39)^MAX(0,15-(Assumptions!C31/12))) -> 0.37172293 | S17: =IF(16<=(Assumptions!C31/12),0,'Revenue Build'!S15*0.01*(1+Assumptions!C39)^MAX(0,16-(Assumptions!C31/12))) -> 0.38941904 | T17: =IF(17<=(Assumptions!C31/12),0,'Revenue Build'!T15*0.01*(1+Assumptions!C39)^MAX(0,17-(Assumptions!C31/12))) -> 0.40814062 | U17: =IF(18<=(Assumptions!C31/12),0,'Revenue Build'!U15*0.01*(1+Assumptions!C39)^MAX(0,18-(Assumptions!C31/12))) -> 0.4279495 | V17: =IF(19<=(Assumptions!C31/12),0,'Revenue Build'!V15*0.01*(1+Assumptions!C39)^MAX(0,19-(Assumptions!C31/12))) -> 0.44891128 | W17: =IF(20<=(Assumptions!C31/12),0,'Revenue Build'!W15*0.01*(1+Assumptions!C39)^MAX(0,20-(Assumptions!C31/12))) -> 0.47109551
B18: Total Variable OPEX | C18: $M | D18: =SUM(D13:D17) -> 0 | E18: =SUM(E13:E17) -> 0 | F18: =SUM(F13:F17) -> 2.4011243 | G18: =SUM(G13:G17) -> 3.7626289 | H18: =SUM(H13:H17) -> 4.6418444 | I18: =SUM(I13:I17) -> 4.8353761 | J18: =SUM(J13:J17) -> 5.0389686 | K18: =SUM(K13:K17) -> 5.2531845 | ... W18: =SUM(W13:W17) -> 8.9076851
B20: OTHER OPERATING COSTS
B21: Management Fee (GP) | C21: $M | D21: =IF(1<=(Assumptions!C31/12),0,'CAPEX Schedule'!C29*0.02) -> 0 | E21: =IF(2<=(Assumptions!C31/12),0,'CAPEX Schedule'!C29*0.02) -> 0 | F21: =IF(3<=(Assumptions!C31/12),0,'CAPEX Schedule'!C29*0.02) -> 1.14144 | G21: =IF(4<=(Assumptions!C31/12),0,'CAPEX Schedule'!C29*0.02) -> 1.14144 | H21: =IF(5<=(Assumptions!C31/12),0,'CAPEX Schedule'!C29*0.02) -> 1.14144 | I21: =IF(6<=(Assumptions!C31/12),0,'CAPEX Schedule'!C29*0.02) -> 1.14144 | J21: =IF(7<=(Assumptions!C31/12),0,'CAPEX Schedule'!C29*0.02) -> 1.14144 | K21: =IF(8<=(Assumptions!C31/12),0,'CAPEX Schedule'!C29*0.02) -> 1.14144 | L21: =IF(9<=(Assumptions!C31/12),0,'CAPEX Schedule'!C29*0.02) -> 1.14144 | M21: =IF(10<=(Assumptions!C31/12),0,'CAPEX Schedule'!C29*0.02) -> 1.14144 | N21: =IF(11<=(Assumptions!C31/12),0,'CAPEX Schedule'!C29*0.02) -> 1.14144 | O21: =IF(12<=(Assumptions!C31/12),0,'CAPEX Schedule'!C29*0.02) -> 1.14144 | P21: =IF(13<=(Assumptions!C31/12),0,'CAPEX Schedule'!C29*0.02) -> 1.14144 | Q21: =IF(14<=(Assumptions!C31/12),0,'CAPEX Schedule'!C29*0.02) -> 1.14144 | R21: =IF(15<=(Assumptions!C31/12),0,'CAPEX Schedule'!C29*0.02) -> 1.14144 | S21: =IF(16<=(Assumptions!C31/12),0,'CAPEX Schedule'!C29*0.02) -> 1.14144 | T21: =IF(17<=(Assumptions!C31/12),0,'CAPEX Schedule'!C29*0.02) -> 1.14144 | U21: =IF(18<=(Assumptions!C31/12),0,'CAPEX Schedule'!C29*0.02) -> 1.14144 | V21: =IF(19<=(Assumptions!C31/12),0,'CAPEX Schedule'!C29*0.02) -> 1.14144 | W21: =IF(20<=(Assumptions!C31/12),0,'CAPEX Schedule'!C29*0.02) -> 1.14144
B22: Political Risk Insurance | C22: $M | D22: ='CAPEX Schedule'!C29*Assumptions!C19 -> 0.85608 | E22: ='CAPEX Schedule'!C29*Assumptions!C19 -> 0.85608 | F22: ='CAPEX Schedule'!C29*Assumptions!C19 -> 0.85608 | G22: ='CAPEX Schedule'!C29*Assumptions!C19 -> 0.85608 | H22: ='CAPEX Schedule'!C29*Assumptions!C19 -> 0.85608 | I22: ='CAPEX Schedule'!C29*Assumptions!C19 -> 0.85608 | J22: ='CAPEX Schedule'!C29*Assumptions!C19 -> 0.85608 | K22: ='CAPEX Schedule'!C29*Assumptions!C19 -> 0.85608 | L22: ='CAPEX Schedule'!C29*Assumptions!C19 -> 0.85608 | M22: ='CAPEX Schedule'!C29*Assumptions!C19 -> 0.85608 | N22: ='CAPEX Schedule'!C29*Assumptions!C19 -> 0.85608 | O22: ='CAPEX Schedule'!C29*Assumptions!C19 -> 0.85608 | P22: ='CAPEX Schedule'!C29*Assumptions!C19 -> 0.85608 | Q22: ='CAPEX Schedule'!C29*Assumptions!C19 -> 0.85608 | R22: ='CAPEX Schedule'!C29*Assumptions!C19 -> 0.85608 | S22: ='CAPEX Schedule'!C29*Assumptions!C19 -> 0.85608 | T22: ='CAPEX Schedule'!C29*Assumptions!C19 -> 0.85608 | U22: ='CAPEX Schedule'!C29*Assumptions!C19 -> 0.85608 | V22: ='CAPEX Schedule'!C29*Assumptions!C19 -> 0.85608 | W22: ='CAPEX Schedule'!C29*Assumptions!C19 -> 0.85608
B23: FX Hedging Costs | C23: $M | D23: =IF(1<=(Assumptions!C31/12),0,'Revenue Build'!D15*0.005) -> 0 | E23: =IF(2<=(Assumptions!C31/12),0,'Revenue Build'!E15*0.005) -> 0 | F23: =IF(3<=(Assumptions!C31/12),0,'Revenue Build'!F15*0.005) -> 0.041690476 | G23: =IF(4<=(Assumptions!C31/12),0,'Revenue Build'!G15*0.005) -> 0.083475782 | H23: =IF(5<=(Assumptions!C31/12),0,'Revenue Build'!H15*0.005) -> 0.10661224 | I23: =IF(6<=(Assumptions!C31/12),0,'Revenue Build'!I15*0.005) -> 0.10685213 | J23: =IF(7<=(Assumptions!C31/12),0,'Revenue Build'!J15*0.005) -> 0.10715089 | K23: =IF(8<=(Assumptions!C31/12),0,'Revenue Build'!K15*0.005) -> 0.10750814 | L23: =IF(9<=(Assumptions!C31/12),0,'Revenue Build'!L15*0.005) -> 0.10792356 | M23: =IF(10<=(Assumptions!C31/12),0,'Revenue Build'!M15*0.005) -> 0.10839686 | N23: =IF(11<=(Assumptions!C31/12),0,'Revenue Build'!N15*0.005) -> 0.10892776 | O23: =IF(12<=(Assumptions!C31/12),0,'Revenue Build'!O15*0.005) -> 0.10951606 | P23: =IF(13<=(Assumptions!C31/12),0,'Revenue Build'!P15*0.005) -> 0.11016156 | Q23: =IF(14<=(Assumptions!C31/12),0,'Revenue Build'!Q15*0.005) -> 0.11086411 | R23: =IF(15<=(Assumptions!C31/12),0,'Revenue Build'!R15*0.005) -> 0.11162358 | S23: =IF(16<=(Assumptions!C31/12),0,'Revenue Build'!S15*0.005) -> 0.11243989 | T23: =IF(17<=(Assumptions!C31/12),0,'Revenue Build'!T15*0.005) -> 0.113313 | U23: =IF(18<=(Assumptions!C31/12),0,'Revenue Build'!U15*0.005) -> 0.11424287 | V23: =IF(19<=(Assumptions!C31/12),0,'Revenue Build'!V15*0.005) -> 0.11522952 | W23: =IF(20<=(Assumptions!C31/12),0,'Revenue Build'!W15*0.005) -> 0.116273
B24: Maintenance CAPEX | C24: $M | D24: =IF(1<=(Assumptions!C31/12),0,'CAPEX Schedule'!C29*Assumptions!C40) -> 0 | E24: =IF(2<=(Assumptions!C31/12),0,'CAPEX Schedule'!C29*Assumptions!C40) -> 0 | F24: =IF(3<=(Assumptions!C31/12),0,'CAPEX Schedule'!C29*Assumptions!C40) -> 1.14144 | G24: =IF(4<=(Assumptions!C31/12),0,'CAPEX Schedule'!C29*Assumptions!C40) -> 1.14144 | H24: =IF(5<=(Assumptions!C31/12),0,'CAPEX Schedule'!C29*Assumptions!C40) -> 1.14144 | I24: =IF(6<=(Assumptions!C31/12),0,'CAPEX Schedule'!C29*Assumptions!C40) -> 1.14144 | J24: =IF(7<=(Assumptions!C31/12),0,'CAPEX Schedule'!C29*Assumptions!C40) -> 1.14144 | K24: =IF(8<=(Assumptions!C31/12),0,'CAPEX Schedule'!C29*Assumptions!C40) -> 1.14144 | L24: =IF(9<=(Assumptions!C31/12),0,'CAPEX Schedule'!C29*Assumptions!C40) -> 1.14144 | M24: =IF(10<=(Assumptions!C31/12),0,'CAPEX Schedule'!C29*Assumptions!C40) -> 1.14144 | N24: =IF(11<=(Assumptions!C31/12),0,'CAPEX Schedule'!C29*Assumptions!C40) -> 1.14144 | O24: =IF(12<=(Assumptions!C31/12),0,'CAPEX Schedule'!C29*Assumptions!C40) -> 1.14144 | P24: =IF(13<=(Assumptions!C31/12),0,'CAPEX Schedule'!C29*Assumptions!C40) -> 1.14144 | Q24: =IF(14<=(Assumptions!C31/12),0,'CAPEX Schedule'!C29*Assumptions!C40) -> 1.14144 | R24: =IF(15<=(Assumptions!C31/12),0,'CAPEX Schedule'!C29*Assumptions!C40) -> 1.14144 | S24: =IF(16<=(Assumptions!C31/12),0,'CAPEX Schedule'!C29*Assumptions!C40) -> 1.14144 | T24: =IF(17<=(Assumptions!C31/12),0,'CAPEX Schedule'!C29*Assumptions!C40) -> 1.14144 | U24: =IF(18<=(Assumptions!C31/12),0,'CAPEX Schedule'!C29*Assumptions!C40) -> 1.14144 | V24: =IF(19<=(Assumptions!C31/12),0,'CAPEX Schedule'!C29*Assumptions!C40) -> 1.14144 | W24: =IF(20<=(Assumptions!C31/12),0,'CAPEX Schedule'!C29*Assumptions!C40) -> 1.14144
B25: Working Capital Change | C25: $M | D25: =IF(1<=Assumptions!C31/12,0,'Revenue Build'!D15*Assumptions!C41/365) -> 0 | E25: =IF(2<=Assumptions!C31/12,0,'Revenue Build'!E15*Assumptions!C41/365-'Revenue Build'!D15*Assumptions!C41/365) -> 0 | F25: =IF(3<=Assumptions!C31/12,0,'Revenue Build'!F15*Assumptions!C41/365-'Revenue Build'!E15*Assumptions!C41/365) -> 1.3706458 | G25: =IF(4<=Assumptions!C31/12,0,'Revenue Build'!G15*Assumptions!C41/365-'Revenue Build'!F15*Assumptions!C41/365) -> 1.3737635 | H25: =IF(5<=Assumptions!C31/12,0,'Revenue Build'!H15*Assumptions!C41/365-'Revenue Build'!G15*Assumptions!C41/365) -> 0.76065077 | I25: =IF(6<=Assumptions!C31/12,0,'Revenue Build'!I15*Assumptions!C41/365-'Revenue Build'!H15*Assumptions!C41/365) -> 0.0078868168 | J25: =IF(7<=Assumptions!C31/12,0,'Revenue Build'!J15*Assumptions!C41/365-'Revenue Build'!I15*Assumptions!C41/365) -> 0.009822107 | K25: =IF(8<=Assumptions!C31/12,0,'Revenue Build'!K15*Assumptions!C41/365-'Revenue Build'!J15*Assumptions!C41/365) -> 0.011745316 | L25: =IF(9<=Assumptions!C31/12,0,'Revenue Build'!L15*Assumptions!C41/365-'Revenue Build'!K15*Assumptions!C41/365) -> 0.013657652 | M25: =IF(10<=Assumptions!C31/12,0,'Revenue Build'!M15*Assumptions!C41/365-'Revenue Build'!L15*Assumptions!C41/365) -> 0.015560309 | N25: =IF(11<=Assumptions!C31/12,0,'Revenue Build'!N15*Assumptions!C41/365-'Revenue Build'!M15*Assumptions!C41/365) -> 0.017454462 | O25: =IF(12<=Assumptions!C31/12,0,'Revenue Build'!O15*Assumptions!C41/365-'Revenue Build'!N15*Assumptions!C41/365) -> 0.019341271 | P25: =IF(13<=Assumptions!C31/12,0,'Revenue Build'!P15*Assumptions!C41/365-'Revenue Build'!O15*Assumptions!C41/365) -> 0.021221881 | Q25: =IF(14<=Assumptions!C31/12,0,'Revenue Build'!Q15*Assumptions!C41/365-'Revenue Build'!P15*Assumptions!C41/365) -> 0.023097424 | R25: =IF(15<=Assumptions!C31/12,0,'Revenue Build'!R15*Assumptions!C41/365-'Revenue Build'!Q15*Assumptions!C41/365) -> 0.024969017 | S25: =IF(16<=Assumptions!C31/12,0,'Revenue Build'!S15*Assumptions!C41/365-'Revenue Build'!R15*Assumptions!C41/365) -> 0.026837767 | T25: =IF(17<=Assumptions!C31/12,0,'Revenue Build'!T15*Assumptions!C41/365-'Revenue Build'!S15*Assumptions!C41/365) -> 0.028704767 | U25: =IF(18<=Assumptions!C31/12,0,'Revenue Build'!U15*Assumptions!C41/365-'Revenue Build'!T15*Assumptions!C41/365) -> 0.0305711 | V25: =IF(19<=Assumptions!C31/12,0,'Revenue Build'!V15*Assumptions!C41/365-'Revenue Build'!U15*Assumptions!C41/365) -> 0.032437838 | W25: =IF(20<=Assumptions!C31/12,0,'Revenue Build'!W15*Assumptions!C41/365-'Revenue Build'!V15*Assumptions!C41/365) -> 0.034306045
B26: Total Other Costs | C26: $M | D26: =SUM(D21:D25) -> 0.85608 | E26: =SUM(E21:E25) -> 0.85608 | F26: =SUM(F21:F25) -> 4.5512963 | G26: =SUM(G21:G25) -> 4.5961993 | H26: =SUM(H21:H25) -> 4.006223 | I26: =SUM(I21:I25) -> 3.253699 | J26: =SUM(J21:J25) -> 3.255933 | K26: =SUM(K21:K25) -> 3.2582135 | ... W26: =SUM(W21:W25) -> 3.289539
B28: TOTAL OPEX | D28: =D10+D18+D26 -> 0.85608 | E28: =E10+E18+E26 -> 0.85608 | F28: =F10+F18+F26 -> 8.7627444 | G28: =G10+G18+G26 -> 10.241565 | H28: =H10+H18+H26 -> 10.606114 | I28: =I10+I18+I26 -> 10.125443 | J28: =J10+J18+J26 -> 10.412724 | K28: =K10+K18+K26 -> 10.713934 | ... W28: =W10+W18+W26 -> 15.723555

Sheet Financing Structure
B1: MULTI-TRANCHE FINANCING & DEBT SERVICE
B3: Financing Component | C3: Unit | D3: 1 | E3: 2 | F3: 3 | G3: 4 | H3: 5 | I3: 6 | J3: 7 | K3: 8 | L3: 9 | M3: 10 | N3: 11 | O3: 12 | P3: 13 | Q3: 14 | R3: 15 | S3: 16 | T3: 17 | U3: 18 | V3: 19 | W3: 20
B4: SOURCES OF FUNDS
B5: Senior Debt Drawdown | C5: $M
B6: Mezzanine Debt Drawdown | C6: $M
B7: DFI/Concessional Drawdown | C7: $M
B8: Equity Injection | C8: $M
B9: Total Sources | C9: $M
B11: SENIOR DEBT SERVICE
B12: Opening Balance | C12: $M | D12: 0 | E12: =D16 -> 15.6948 | F12: =E16 -> 31.3896 | G12: =F16 -> 31.3896 | H12: =G16 -> 31.3896 | I12: =H16 -> 27.901867 | J12: =I16 -> 24.414133 | K12: =J16 -> 20.9264 | L12: =K16 -> 17.438667 | ... W12: =V16 -> 0
B13: Drawdowns | C13: $M | D13: =IF(1<=(Assumptions!C31/12),'CAPEX Schedule'!C29*Assumptions!C46/(Assumptions!C31/12),0) -> 15.6948 | E13: =IF(2<=(Assumptions!C31/12),'CAPEX Schedule'!C29*Assumptions!C46/(Assumptions!C31/12),0) -> 15.6948 | F13: =IF(3<=(Assumptions!C31/12),'CAPEX Schedule'!C29*Assumptions!C46/(Assumptions!C31/12),0) -> 0 | G13: =IF(4<=(Assumptions!C31/12),'CAPEX Schedule'!C29*Assumptions!C46/(Assumptions!C31/12),0) -> 0 | H13: =IF(5<=(Assumptions!C31/12),'CAPEX Schedule'!C29*Assumptions!C46/(Assumptions!C31/12),0) -> 0 | I13: =IF(6<=(Assumptions!C31/12),'CAPEX Schedule'!C29*Assumptions!C46/(Assumptions!C31/12),0) -> 0 | J13: =IF(7<=(Assumptions!C31/12),'CAPEX Schedule'!C29*Assumptions!C46/(Assumptions!C31/12),0) -> 0 | K13: =IF(8<=(Assumptions!C31/12),'CAPEX Schedule'!C29*Assumptions!C46/(Assumptions!C31/12),0) -> 0 | L13: =IF(9<=(Assumptions!C31/12),'CAPEX Schedule'!C29*Assumptions!C46/(Assumptions!C31/12),0) -> 0 | M13: =IF(10<=(Assumptions!C31/12),'CAPEX Schedule'!C29*Assumptions!C46/(Assumptions!C31/12),0) -> 0 | N13: =IF(11<=(Assumptions!C31/12),'CAPEX Schedule'!C29*Assumptions!C46/(Assumptions!C31/12),0) -> 0 | O13: =IF(12<=(Assumptions!C31/12),'CAPEX Schedule'!C29*Assumptions!C46/(Assumptions!C31/12),0) -> 0 | P13: =IF(13<=(Assumptions!C31/12),'CAPEX Schedule'!C29*Assumptions!C46/(Assumptions!C31/12),0) -> 0 | Q13: =IF(14<=(Assumptions!C31/12),'CAPEX Schedule'!C29*Assumptions!C46/(Assumptions!C31/12),0) -> 0 | R13: =IF(15<=(Assumptions!C31/12),'CAPEX Schedule'!C29*Assumptions!C46/(Assumptions!C31/12),0) -> 0 | S13: =IF(16<=(Assumptions!C31/12),'CAPEX Schedule'!C29*Assumptions!C46/(Assumptions!C31/12),0) -> 0 | T13: =IF(17<=(Assumptions!C31/12),'CAPEX Schedule'!C29*Assumptions!C46/(Assumptions!C31/12),0) -> 0 | U13: =IF(18<=(Assumptions!C31/12),'CAPEX Schedule'!C29*Assumptions!C46/(Assumptions!C31/12),0) -> 0 | V13: =IF(19<=(Assumptions!C31/12),'CAPEX Schedule'!C29*Assumptions!C46/(Assumptions!C31/12),0) -> 0 | W13: =IF(20<=(Assumptions!C31/12),'CAPEX Schedule'!C29*Assumptions!C46/(Assumptions!C31/12),0) -> 0
B14: Scheduled Repayment | C14: $M | D14: =IFERROR(IF(1<=(Assumptions!C31/12)+Assumptions!C49,0,IF(Assumptions!C47-(1-(Assumptions!C31/12))<=0,0,-(D12+D13)/MAX(1,Assumptions!C47-(1-(Assumptions!C31/12))))),0) -> 0 | E14: =IFERROR(IF(2<=(Assumptions!C31/12)+Assumptions!C49,0,IF(Assumptions!C47-(2-(Assumptions!C31/12))<=0,0,-(E12+E13)/MAX(1,Assumptions!C47-(2-(Assumptions!C31/12))))),0) -> 0 | F14: =IFERROR(IF(3<=(Assumptions!C31/12)+Assumptions!C49,0,IF(Assumptions!C47-(3-(Assumptions!C31/12))<=0,0,-(F12+F13)/MAX(1,Assumptions!C47-(3-(Assumptions!C31/12))))),0) -> 0 | G14: =IFERROR(IF(4<=(Assumptions!C31/12)+Assumptions!C49,0,IF(Assumptions!C47-(4-(Assumptions!C31/12))<=0,0,-(G12+G13)/MAX(1,Assumptions!C47-(4-(Assumptions!C31/12))))),0) -> 0 | H14: =IFERROR(IF(5<=(Assumptions!C31/12)+Assumptions!C49,0,IF(Assumptions!C47-(5-(Assumptions!C31/12))<=0,0,-(H12+H13)/MAX(1,Assumptions!C47-(5-(Assumptions!C31/12))))),0) -> -3.4877333 | I14: =IFERROR(IF(6<=(Assumptions!C31/12)+Assumptions!C49,0,IF(Assumptions!C47-(6-(Assumptions!C31/12))<=0,0,-(I12+I13)/MAX(1,Assumptions!C47-(6-(Assumptions!C31/12))))),0) -> -3.4877333 | J14: =IFERROR(IF(7<=(Assumptions!C31/12)+Assumptions!C49,0,IF(Assumptions!C47-(7-(Assumptions!C31/12))<=0,0,-(J12+J13)/MAX(1,Assumptions!C47-(7-(Assumptions!C31/12))))),0) -> -3.4877333 | K14: =IFERROR(IF(8<=(Assumptions!C31/12)+Assumptions!C49,0,IF(Assumptions!C47-(8-(Assumptions!C31/12))<=0,0,-(K12+K13)/MAX(1,Assumptions!C47-(8-(Assumptions!C31/12))))),0) -> -3.4877333 | L14: =IFERROR(IF(9<=(Assumptions!C31/12)+Assumptions!C49,0,IF(Assumptions!C47-(9-(Assumptions!C31/12))<=0,0,-(L12+L13)/MAX(1,Assumptions!C47-(9-(Assumptions!C31/12))))),0) -> -3.4877333 | M14: =IFERROR(IF(10<=(Assumptions!C31/12)+Assumptions!C49,0,IF(Assumptions!C47-(10-(Assumptions!C31/12))<=0,0,-(M12+M13)/MAX(1,Assumptions!C47-(10-(Assumptions!C31/12))))),0) -> -3.4877333 | N14: =IFERROR(IF(11<=(Assumptions!C31/12)+Assumptions!C49,0,IF(Assumptions!C47-(11-(Assumptions!C31/12))<=0,0,-(N12+N13)/MAX(1,Assumptions!C47-(11-(Assumptions!C31/12))))),0) -> -3.4877333 | O14: =IFERROR(IF(12<=(Assumptions!C31/12)+Assumptions!C49,0,IF(Assumptions!C47-(12-(Assumptions!C31/12))<=0,0,-(O12+O13)/MAX(1,Assumptions!C47-(12-(Assumptions!C31/12))))),0) -> -3.4877333 | P14: =IFERROR(IF(13<=(Assumptions!C31/12)+Assumptions!C49,0,IF(Assumptions!C47-(13-(Assumptions!C31/12))<=0,0,-(P12+P13)/MAX(1,Assumptions!C47-(13-(Assumptions!C31/12))))),0) -> -3.4877333 | Q14: =IFERROR(IF(14<=(Assumptions!C31/12)+Assumptions!C49,0,IF(Assumptions!C47-(14-(Assumptions!C31/12))<=0,0,-(Q12+Q13)/MAX(1,Assumptions!C47-(14-(Assumptions!C31/12))))),0) -> 0 | R14: =IFERROR(IF(15<=(Assumptions!C31/12)+Assumptions!C49,0,IF(Assumptions!C47-(15-(Assumptions!C31/12))<=0,0,-(R12+R13)/MAX(1,Assumptions!C47-(15-(Assumptions!C31/12))))),0) -> 0 | S14: =IFERROR(IF(16<=(Assumptions!C31/12)+Assumptions!C49,0,IF(Assumptions!C47-(16-(Assumptions!C31/12))<=0,0,-(S12+S13)/MAX(1,Assumptions!C47-(16-(Assumptions!C31/12))))),0) -> 0 | T14: =IFERROR(IF(17<=(Assumptions!C31/12)+Assumptions!C49,0,IF(Assumptions!C47-(17-(Assumptions!C31/12))<=0,0,-(T12+T13)/MAX(1,Assumptions!C47-(17-(Assumptions!C31/12))))),0) -> 0 | U14: =IFERROR(IF(18<=(Assumptions!C31/12)+Assumptions!C49,0,IF(Assumptions!C47-(18-(Assumptions!C31/12))<=0,0,-(U12+U13)/MAX(1,Assumptions!C47-(18-(Assumptions!C31/12))))),0) -> 0 | V14: =IFERROR(IF(19<=(Assumptions!C31/12)+Assumptions!C49,0,IF(Assumptions!C47-(19-(Assumptions!C31/12))<=0,0,-(V12+V13)/MAX(1,Assumptions!C47-(19-(Assumptions!C31/12))))),0) -> 0 | W14: =IFERROR(IF(20<=(Assumptions!C31/12)+Assumptions!C49,0,IF(Assumptions!C47-(20-(Assumptions!C31/12))<=0,0,-(W12+W13)/MAX(1,Assumptions!C47-(20-(Assumptions!C31/12))))),0) -> 0
B15: Cash Sweep Repayment | C15: $M | D15: 0 | E15: 0 | F15: 0 | G15: 0 | H15: 0 | I15: 0 | J15: 0 | K15: 0 | L15: 0 | M15: 0 | N15: 0 | O15: 0 | P15: 0 | Q15: 0 | R15: 0 | S15: 0 | T15: 0 | U15: 0 | V15: 0 | W15: 0
B16: Closing Balance | C16: $M | D16: =MAX(0,D12+D13+D14+D15) -> 15.6948 | E16: =MAX(0,E12+E13+E14+E15) -> 31.3896 | F16: =MAX(0,F12+F13+F14+F15) -> 31.3896 | G16: =MAX(0,G12+G13+G14+G15) -> 31.3896 | H16: =MAX(0,H12+H13+H14+H15) -> 27.901867 | I16: =MAX(0,I12+I13+I14+I15) -> 24.414133 | J16: =MAX(0,J12+J13+J14+J15) -> 20.9264 | K16: =MAX(0,K12+K13+K14+K15) -> 17.438667 | ... W16: =MAX(0,W12+W13+W14+W15) -> 0
B17: Interest Expense | C17: $M | D17: =-(D12+D16)/2*Assumptions!C48 -> -0.667029 | E17: =-(E12+E16)/2*Assumptions!C48 -> -2.001087 | F17: =-(F12+F16)/2*Assumptions!C48 -> -2.668116 | G17: =-(G12+G16)/2*Assumptions!C48 -> -2.668116 | H17: =-(H12+H16)/2*Assumptions!C48 -> -2.5198873 | I17: =-(I12+I16)/2*Assumptions!C48 -> -2.22343 | J17: =-(J12+J16)/2*Assumptions!C48 -> -1.9269727 | K17: =-(K12+K16)/2*Assumptions!C48 -> -1.6305153 | L17: =-(L12+L16)/2*Assumptions!C48 -> -1.334058 | M17: =-(M12+M16)/2*Assumptions!C48 -> -1.0376007 | N17: =-(N12+N16)/2*Assumptions!C48 -> -0.74114333 | O17: =-(O12+O16)/2*Assumptions!C48 -> -0.444686 | P17: =-(P12+P16)/2*Assumptions!C48 -> -0.14822867 | Q17: =-(Q12+Q16)/2*Assumptions!C48 -> 0 | R17: =-(R12+R16)/2*Assumptions!C48 -> 0 | S17: =-(S12+S16)/2*Assumptions!C48 -> 0 | T17: =-(T12+T16)/2*Assumptions!C48 -> 0 | U17: =-(U12+U16)/2*Assumptions!C48 -> 0 | V17: =-(V12+V16)/2*Assumptions!C48 -> 0 | W17: =-(W12+W16)/2*Assumptions!C48 -> 0
B18: Total Senior Debt Service | C18: $M | D18: =D14+D15+D17 -> -0.667029 | E18: =E14+E15+E17 -> -2.001087 | F18: =F14+F15+F17 -> -2.668116 | G18: =G14+G15+G17 -> -2.668116 | H18: =H14+H15+H17 -> -6.0076207 | I18: =I14+I15+I17 -> -5.7111633 | J18: =J14+J15+J17 -> -5.414706 | K18: =K14+K15+K17 -> -5.1182487 | ... W18: =W14+W15+W17 -> 0
B20: MEZZANINE DEBT SERVICE
B21: Opening Balance | C21: $M
B22: Drawdowns | C22: $M
B23: Scheduled Repayment | C23: $M
B24: Closing Balance | C24: $M
B25: Interest Expense (PIK + Cash) | C25: $M
B26: Total Mezz Debt Service | C26: $M
B28: DFI/CONCESSIONAL LAYER
B29: Opening Balance | C29: $M
B30: Drawdowns | C30: $M
B31: Scheduled Repayment | C31: $M
B32: Closing Balance | C32: $M
B33: Interest Expense | C33: $M
B34: Total DFI Debt Service | C34: $M
B36: AGGREGATE DEBT METRICS
B37: Total Debt Outstanding | C37: $M | D37: =D16+D24+D32 -> 15.6948 | E37: =E16+E24+E32 -> 31.3896 | F37: =F16+F24+F32 -> 31.3896 | G37: =G16+G24+G32 -> 31.3896 | H37: =H16+H24+H32 -> 27.901867 | I37: =I16+I24+I32 -> 24.414133 | J37: =J16+J24+J32 -> 20.9264 | K37: =K16+K24+K32 -> 17.438667 | ... W37: =W16+W24+W32 -> 0
B38: Total Interest Expense | C38: $M | D38: =D17+D25+D33 -> -0.667029 | E38: =E17+E25+E33 -> -2.001087 | F38: =F17+F25+F33 -> -2.668116 | G38: =G17+G25+G33 -> -2.668116 | H38: =H17+H25+H33 -> -2.5198873 | I38: =I17+I25+I33 -> -2.22343 | J38: =J17+J25+J33 -> -1.9269727 | K38: =K17+K25+K33 -> -1.6305153 | ... W38: =W17+W25+W33 -> 0
B39: Total Principal Repayment | C39: $M | D39: =D14+D23+D31 -> 0 | E39: =E14+E23+E31 -> 0 | F39: =F14+F23+F31 -> 0 | G39: =G14+G23+G31 -> 0 | H39: =H14+H23+H31 -> -3.4877333 | I39: =I14+I23+I31 -> -3.4877333 | J39: =J14+J23+J31 -> -3.4877333 | K39: =K14+K23+K31 -> -3.4877333 | ... W39: =W14+W23+W31 -> 0
B40: Total Debt Service | C40: $M | D40: =D38+D39 -> -0.667029 | E40: =E38+E39 -> -2.001087 | F40: =F38+F39 -> -2.668116 | G40: =G38+G39 -> -2.668116 | H40: =H38+H39 -> -6.0076207 | I40: =I38+I39 -> -5.7111633 | J40: =J38+J39 -> -5.414706 | K40: =K38+K39 -> -5.1182487 | ... W40: =W38+W39 -> 0
B41: DSCR (Debt Service Coverage Ratio) | C41: x | D41: =IFERROR(IF(ABS(D40)<0.001,"-",'Cash Flow Waterfall'!D14/ABS(D40)),"-") -> -1.2834225 | E41: =IFERROR(IF(ABS(E40)<0.001,"-",'Cash Flow Waterfall'!E14/ABS(E40)),"-") -> -0.42780749 | F41: =IFERROR(IF(ABS(F40)<0.001,"-",'Cash Flow Waterfall'!F14/ABS(F40)),"-") -> -1.0982882 | G41: =IFERROR(IF(ABS(G40)<0.001,"-",'Cash Flow Waterfall'!G14/ABS(G40)),"-") -> 0.96716407 | H41: =IFERROR(IF(ABS(H40)<0.001,"-",'Cash Flow Waterfall'!H14/ABS(H40)),"-") -> 1.0130693 | I41: =IFERROR(IF(ABS(I40)<0.001,"-",'Cash Flow Waterfall'!I14/ABS(I40)),"-") -> 1.1568457 | J41: =IFERROR(IF(ABS(J40)<0.001,"-",'Cash Flow Waterfall'!J14/ABS(J40)),"-") -> 1.1763572 | K41: =IFERROR(IF(ABS(K40)<0.001,"-",'Cash Flow Waterfall'!K14/ABS(K40)),"-") -> 0.93847985 | ... W41: =IFERROR(IF(ABS(W40)<0.001,"-",'Cash Flow Waterfall'!W14/ABS(W40)),"-") -> -
B42: LLCR (Loan Life Coverage Ratio) | C42: x
B43: Debt / Equity Ratio | C43: x

Sheet Cash Flow Waterfall
B1: INTEGRATED CASH FLOW WATERFALL
B3: Cash Flow Item | C3: Unit | D3: 1 | E3: 2 | F3: 3 | G3: 4 | H3: 5 | I3: 6 | J3: 7 | K3: 8 | L3: 9 | M3: 10 | N3: 11 | O3: 12 | P3: 13 | Q3: 14 | R3: 15 | S3: 16 | T3: 17 | U3: 18 | V3: 19 | W3: 20
B4: PROJECT CASH FLOWS
B5: Net Revenue (from Revenue Build) | C5: $M | D5: ='Revenue Build'!D21 -> 0 | E5: ='Revenue Build'!E21 -> 0 | F5: ='Revenue Build'!F21 -> 6.973824 | G5: ='Revenue Build'!G21 -> 13.963511 | H5: ='Revenue Build'!H21 -> 17.83369 | I5: ='Revenue Build'!I21 -> 17.873818 | J5: ='Revenue Build'!J21 -> 17.923793 | K5: ='Revenue Build'!K21 -> 17.983553 | ... W5: ='Revenue Build'!W21 -> 19.449704
B6: Less: Total OPEX | C6: $M | D6: =-'OPEX Schedule'!D28 -> -0.85608 | E6: =-'OPEX Schedule'!E28 -> -0.85608 | F6: =-'OPEX Schedule'!F28 -> -8.7627444 | G6: =-'OPEX Schedule'!G28 -> -10.241565 | H6: =-'OPEX Schedule'!H28 -> -10.606114 | I6: =-'OPEX Schedule'!I28 -> -10.125443 | J6: =-'OPEX Schedule'!J28 -> -10.412724 | K6: =-'OPEX Schedule'!K28 -> -10.713934 | ... W6: =-'OPEX Schedule'!W28 -> -15.723555
B7: EBITDA | C7: $M | D7: =D5+D6 -> -0.85608 | E7: =E5+E6 -> -0.85608 | F7: =F5+F6 -> -1.7889203 | G7: =G5+G6 -> 3.7219459 | H7: =H5+H6 -> 7.2275762 | I7: =I5+I6 -> 7.7483747 | J7: =J5+J6 -> 7.5110682 | K7: =K5+K6 -> 7.2696189 | ... W7: =W5+W6 -> 3.7261489
B8: Less: Depreciation (straight-line) | C8: $M | D8: =IF(1<=Assumptions!C31/12,0,-'CAPEX Schedule'!C29/Assumptions!C32) -> 0 | E8: =IF(2<=Assumptions!C31/12,0,-'CAPEX Schedule'!C29/Assumptions!C32) -> 0 | F8: =IF(3<=Assumptions!C31/12,0,-'CAPEX Schedule'!C29/Assumptions!C32) -> -2.8536 | G8: =IF(4<=Assumptions!C31/12,0,-'CAPEX Schedule'!C29/Assumptions!C32) -> -2.8536 | H8: =IF(5<=Assumptions!C31/12,0,-'CAPEX Schedule'!C29/Assumptions!C32) -> -2.8536 | I8: =IF(6<=Assumptions!C31/12,0,-'CAPEX Schedule'!C29/Assumptions!C32) -> -2.8536 | J8: =IF(7<=Assumptions!C31/12,0,-'CAPEX Schedule'!C29/Assumptions!C32) -> -2.8536 | K8: =IF(8<=Assumptions!C31/12,0,-'CAPEX Schedule'!C29/Assumptions!C32) -> -2.8536 | L8: =IF(9<=Assumptions!C31/12,0,-'CAPEX Schedule'!C29/Assumptions!C32) -> -2.8536 | M8: =IF(10<=Assumptions!C31/12,0,-'CAPEX Schedule'!C29/Assumptions!C32) -> -2.8536 | N8: =IF(11<=Assumptions!C31/12,0,-'CAPEX Schedule'!C29/Assumptions!C32) -> -2.8536 | O8: =IF(12<=Assumptions!C31/12,0,-'CAPEX Schedule'!C29/Assumptions!C32) -> -2.8536 | P8: =IF(13<=Assumptions!C31/12,0,-'CAPEX Schedule'!C29/Assumptions!C32) -> -2.8536 | Q8: =IF(14<=Assumptions!C31/12,0,-'CAPEX Schedule'!C29/Assumptions!C32) -> -2.8536 | R8: =IF(15<=Assumptions!C31/12,0,-'CAPEX Schedule'!C29/Assumptions!C32) -> -2.8536 | S8: =IF(16<=Assumptions!C31/12,0,-'CAPEX Schedule'!C29/Assumptions!C32) -> -2.8536 | T8: =IF(17<=Assumptions!C31/12,0,-'CAPEX Schedule'!C29/Assumptions!C32) -> -2.8536 | U8: =IF(18<=Assumptions!C31/12,0,-'CAPEX Schedule'!C29/Assumptions!C32) -> -2.8536 | V8: =IF(19<=Assumptions!C31/12,0,-'CAPEX Schedule'!C29/Assumptions!C32) -> -2.8536 | W8: =IF(20<=Assumptions!C31/12,0,-'CAPEX Schedule'!C29/Assumptions!C32) -> -2.8536
B9: Taxable Income | C9: $M | D9: =D7+D8 -> -0.85608 | E9: =E7+E8 -> -0.85608 | F9: =F7+F8 -> -4.6425203 | G9: =G7+G8 -> 0.86834592 | H9: =H7+H8 -> 4.3739762 | I9: =I7+I8 -> 4.8947747 | J9: =J7+J8 -> 4.6574682 | K9: =K7+K8 -> 4.4160189 | ... W9: =W7+W8 -> 0.87254886
B10: Less: Corporate Tax | C10: $M | D10: =IF(MAX(0,1-Assumptions!C31/12)<=Assumptions!C23,0,-MAX(0,D9)*Assumptions!C20) -> 0 | E10: =IF(MAX(0,2-Assumptions!C31/12)<=Assumptions!C23,0,-MAX(0,E9)*Assumptions!C20) -> 0 | F10: =IF(MAX(0,3-Assumptions!C31/12)<=Assumptions!C23,0,-MAX(0,F9)*Assumptions!C20) -> 0 | G10: =IF(MAX(0,4-Assumptions!C31/12)<=Assumptions!C23,0,-MAX(0,G9)*Assumptions!C20) -> 0 | H10: =IF(MAX(0,5-Assumptions!C31/12)<=Assumptions!C23,0,-MAX(0,H9)*Assumptions!C20) -> 0 | I10: =IF(MAX(0,6-Assumptions!C31/12)<=Assumptions!C23,0,-MAX(0,I9)*Assumptions!C20) -> 0 | J10: =IF(MAX(0,7-Assumptions!C31/12)<=Assumptions!C23,0,-MAX(0,J9)*Assumptions!C20) -> 0 | K10: =IF(MAX(0,8-Assumptions!C31/12)<=Assumptions!C23,0,-MAX(0,K9)*Assumptions!C20) -> -1.3248057 | L10: =IF(MAX(0,9-Assumptions!C31/12)<=Assumptions!C23,0,-MAX(0,L9)*Assumptions!C20) -> -1.2508937 | M10: =IF(MAX(0,10-Assumptions!C31/12)<=Assumptions!C23,0,-MAX(0,M9)*Assumptions!C20) -> -1.1752601 | N10: =IF(MAX(0,11-Assumptions!C31/12)<=Assumptions!C23,0,-MAX(0,N9)*Assumptions!C20) -> -1.0976496 | O10: =IF(MAX(0,12-Assumptions!C31/12)<=Assumptions!C23,0,-MAX(0,O9)*Assumptions!C20) -> -1.0177956 | P10: =IF(MAX(0,13-Assumptions!C31/12)<=Assumptions!C23,0,-MAX(0,P9)*Assumptions!C20) -> -0.9354192 | Q10: =IF(MAX(0,14-Assumptions!C31/12)<=Assumptions!C23,0,-MAX(0,Q9)*Assumptions!C20) -> -0.85022848 | R10: =IF(MAX(0,15-Assumptions!C31/12)<=Assumptions!C23,0,-MAX(0,R9)*Assumptions!C20) -> -0.76191756 | S10: =IF(MAX(0,16-Assumptions!C31/12)<=Assumptions!C23,0,-MAX(0,S9)*Assumptions!C20) -> -0.67016582 | T10: =IF(MAX(0,17-Assumptions!C31/12)<=Assumptions!C23,0,-MAX(0,T9)*Assumptions!C20) -> -0.57463685 | U10: =IF(MAX(0,18-Assumptions!C31/12)<=Assumptions!C23,0,-MAX(0,U9)*Assumptions!C20) -> -0.47497747 | V10: =IF(MAX(0,19-Assumptions!C31/12)<=Assumptions!C23,0,-MAX(0,V9)*Assumptions!C20) -> -0.37081672 | W10: =IF(MAX(0,20-Assumptions!C31/12)<=Assumptions!C23,0,-MAX(0,W9)*Assumptions!C20) -> -0.26176466
B11: Net Income | C11: $M | D11: =D9+D10 -> -0.85608 | E11: =E9+E10 -> -0.85608 | F11: =F9+F10 -> -4.6425203 | G11: =G9+G10 -> 0.86834592 | H11: =H9+H10 -> 4.3739762 | I11: =I9+I10 -> 4.8947747 | J11: =J9+J10 -> 4.6574682 | K11: =K9+K10 -> 3.0912132 | ... W11: =W9+W10 -> 0.6107842
B12: Add Back: Depreciation | C12: $M | D12: =-D8 -> 0 | E12: =-E8 -> 0 | F12: =-F8 -> 2.8536 | G12: =-G8 -> 2.8536 | H12: =-H8 -> 2.8536 | I12: =-I8 -> 2.8536 | J12: =-J8 -> 2.8536 | K12: =-K8 -> 2.8536 | ... W12: =-W8 -> 2.8536
B13: Less: Maintenance CAPEX | C13: $M | D13: =IF(1<=Assumptions!C31/12,0,-'CAPEX Schedule'!C29*Assumptions!C40) -> 0 | E13: =IF(2<=Assumptions!C31/12,0,-'CAPEX Schedule'!C29*Assumptions!C40) -> 0 | F13: =IF(3<=Assumptions!C31/12,0,-'CAPEX Schedule'!C29*Assumptions!C40) -> -1.14144 | G13: =IF(4<=Assumptions!C31/12,0,-'CAPEX Schedule'!C29*Assumptions!C40) -> -1.14144 | H13: =IF(5<=Assumptions!C31/12,0,-'CAPEX Schedule'!C29*Assumptions!C40) -> -1.14144 | I13: =IF(6<=Assumptions!C31/12,0,-'CAPEX Schedule'!C29*Assumptions!C40) -> -1.14144 | J13: =IF(7<=Assumptions!C31/12,0,-'CAPEX Schedule'!C29*Assumptions!C40) -> -1.14144 | K13: =IF(8<=Assumptions!C31/12,0,-'CAPEX Schedule'!C29*Assumptions!C40) -> -1.14144 | L13: =IF(9<=Assumptions!C31/12,0,-'CAPEX Schedule'!C29*Assumptions!C40) -> -1.14144 | M13: =IF(10<=Assumptions!C31/12,0,-'CAPEX Schedule'!C29*Assumptions!C40) -> -1.14144 | N13: =IF(11<=Assumptions!C31/12,0,-'CAPEX Schedule'!C29*Assumptions!C40) -> -1.14144 | O13: =IF(12<=Assumptions!C31/12,0,-'CAPEX Schedule'!C29*Assumptions!C40) -> -1.14144 | P13: =IF(13<=Assumptions!C31/12,0,-'CAPEX Schedule'!C29*Assumptions!C40) -> -1.14144 | Q13: =IF(14<=Assumptions!C31/12,0,-'CAPEX Schedule'!C29*Assumptions!C40) -> -1.14144 | R13: =IF(15<=Assumptions!C31/12,0,-'CAPEX Schedule'!C29*Assumptions!C40) -> -1.14144 | S13: =IF(16<=Assumptions!C31/12,0,-'CAPEX Schedule'!C29*Assumptions!C40) -> -1.14144 | T13: =IF(17<=Assumptions!C31/12,0,-'CAPEX Schedule'!C29*Assumptions!C40) -> -1.14144 | U13: =IF(18<=Assumptions!C31/12,0,-'CAPEX Schedule'!C29*Assumptions!C40) -> -1.14144 | V13: =IF(19<=Assumptions!C31/12,0,-'CAPEX Schedule'!C29*Assumptions!C40) -> -1.14144 | W13: =IF(20<=Assumptions!C31/12,0,-'CAPEX Schedule'!C29*Assumptions!C40) -> -1.14144
B14: Cash Flow Available for Debt Service (CFADS) | C14: $M | D14: =D11+D12+D13 -> -0.85608 | E14: =E11+E12+E13 -> -0.85608 | F14: =F11+F12+F13 -> -2.9303603 | G14: =G11+G12+G13 -> 2.5805059 | H14: =H11+H12+H13 -> 6.0861362 | I14: =I11+I12+I13 -> 6.6069347 | J14: =J11+J12+J13 -> 6.3696282 | K14: =K11+K12+K13 -> 4.8033732 | ... W14: =W11+W12+W13 -> 2.3229442
B16: DEBT SERVICE WATERFALL
B17: Less: Senior Debt Service | C17: $M | D17: ='Financing Structure'!D18 -> -0.667029 | E17: ='Financing Structure'!E18 -> -2.001087 | F17: ='Financing Structure'!F18 -> -2.668116 | G17: ='Financing Structure'!G18 -> -2.668116 | H17: ='Financing Structure'!H18 -> -6.0076207 | I17: ='Financing Structure'!I18 -> -5.7111633 | J17: ='Financing Structure'!J18 -> -5.414706 | K17: ='Financing Structure'!K18 -> -5.1182487 | ... W17: ='Financing Structure'!W18 -> 0
B18: Less: Mezzanine Debt Service | C18: $M | D18: ='Financing Structure'!D26 -> 0 | E18: ='Financing Structure'!E26 -> 0 | F18: ='Financing Structure'!F26 -> 0 | G18: ='Financing Structure'!G26 -> 0 | H18: ='Financing Structure'!H26 -> 0 | I18: ='Financing Structure'!I26 -> 0 | J18: ='Financing Structure'!J26 -> 0 | K18: ='Financing Structure'!K26 -> 0 | ... W18: ='Financing Structure'!W26 -> 0
B19: Less: DFI Debt Service | C19: $M | D19: ='Financing Structure'!D34 -> 0 | E19: ='Financing Structure'!E34 -> 0 | F19: ='Financing Structure'!F34 -> 0 | G19: ='Financing Structure'!G34 -> 0 | H19: ='Financing Structure'!H34 -> 0 | I19: ='Financing Structure'!I34 -> 0 | J19: ='Financing Structure'!J34 -> 0 | K19: ='Financing Structure'!K34 -> 0 | ... W19: ='Financing Structure'!W34 -> 0
B20: Cash Flow After Debt Service (CFADS-DS) | C20: $M | D20: =D14+D17+D18+D19 -> -1.523109 | E20: =E14+E17+E18+E19 -> -2.857167 | F20: =F14+F17+F18+F19 -> -5.5984763 | G20: =G14+G17+G18+G19 -> -0.087610079 | H20: =H14+H17+H18+H19 -> 0.078515515 | I20: =I14+I17+I18+I19 -> 0.89577141 | J20: =J14+J17+J18+J19 -> 0.95492216 | K20: =K14+K17+K18+K19 -> -0.31487543 | ... W20: =W14+W17+W18+W19 -> 2.3229442
B22: EQUITY CASH FLOWS
B23: Less: DSRA Funding/(Release) | C23: $M | D23: 0 | E23: 0 | F23: 0 | G23: 0 | H23: 0 | I23: 0 | J23: 0 | K23: 0 | L23: 0 | M23: 0 | N23: 0 | O23: 0 | P23: 0 | Q23: 0 | R23: 0 | S23: 0 | T23: 0 | U23: 0 | V23: 0 | W23: 0
B24: Less: Cash Sweep (if applicable) | C24: $M | D24: 0 | E24: 0 | F24: 0 | G24: 0 | H24: 0 | I24: 0 | J24: 0 | K24: 0 | L24: 0 | M24: 0 | N24: 0 | O24: 0 | P24: 0 | Q24: 0 | R24: 0 | S24: 0 | T24: 0 | U24: 0 | V24: 0 | W24: 0
B25: Free Cash Flow to Equity (FCFE) | C25: $M | D25: =D20+D23+D24 -> -1.523109 | E25: =E20+E23+E24 -> -2.857167 | F25: =F20+F23+F24 -> -5.5984763 | G25: =G20+G23+G24 -> -0.087610079 | H25: =H20+H23+H24 -> 0.078515515 | I25: =I20+I23+I24 -> 0.89577141 | J25: =J20+J23+J24 -> 0.95492216 | K25: =K20+K23+K24 -> -0.31487543 | ... W25: =W20+W23+W24 -> 2.3229442
B26: Less: Withholding Tax on Distributions | C26: $M | D26: =-MAX(0,D25)*Assumptions!C20 -> 0 | E26: =-MAX(0,E25)*Assumptions!C20 -> 0 | F26: =-MAX(0,F25)*Assumptions!C20 -> 0 | G26: =-MAX(0,G25)*Assumptions!C20 -> 0 | H26: =-MAX(0,H25)*Assumptions!C20 -> -0.023554654 | I26: =-MAX(0,I25)*Assumptions!C20 -> -0.26873142 | J26: =-MAX(0,J25)*Assumptions!C20 -> -0.28647665 | K26: =-MAX(0,K25)*Assumptions!C20 -> 0 | L26: =-MAX(0,L25)*Assumptions!C20 -> 0 | M26: =-MAX(0,M25)*Assumptions!C20 -> 0 | N26: =-MAX(0,N25)*Assumptions!C20 -> -0.013339705 | O26: =-MAX(0,O25)*Assumptions!C20 -> -0.046379114 | P26: =-MAX(0,P25)*Assumptions!C20 -> -0.077652843 | Q26: =-MAX(0,Q25)*Assumptions!C20 -> -1.1088079 | R26: =-MAX(0,R25)*Assumptions!C20 -> -1.0469903 | S26: =-MAX(0,S25)*Assumptions!C20 -> -0.98276407 | T26: =-MAX(0,T25)*Assumptions!C20 -> -0.91589379 | U26: =-MAX(0,U25)*Assumptions!C20 -> -0.84613223 | V26: =-MAX(0,V25)*Assumptions!C20 -> -0.7732197 | W26: =-MAX(0,W25)*Assumptions!C20 -> -0.69688326
B27: Net Distributable Cash Flow | C27: $M | D27: =D25+D26 -> -1.523109 | E27: =E25+E26 -> -2.857167 | F27: =F25+F26 -> -5.5984763 | G27: =G25+G26 -> -0.087610079 | H27: =H25+H26 -> 0.05496086 | I27: =I25+I26 -> 0.62703999 | J27: =J25+J26 -> 0.66844551 | K27: =K25+K26 -> -0.31487543 | ... W27: =W25+W26 -> 1.6260609
B29: FUND-LEVEL CASH FLOWS
B30: Fund's Share of Distributions (at equity %) | C30: $M | D30: =D27*Assumptions!C33 -> -22.846635 | E30: =E27*Assumptions!C33 -> -42.857505 | F30: =F27*Assumptions!C33 -> -83.977145 | G30: =G27*Assumptions!C33 -> -1.3141512 | H30: =H27*Assumptions!C33 -> 0.8244129 | I30: =I27*Assumptions!C33 -> 9.4055998 | J30: =J27*Assumptions!C33 -> 10.026683 | K30: =K27*Assumptions!C33 -> -4.7231314 | L30: =L27*Assumptions!C33 -> -2.8631906 | M30: =M27*Assumptions!C33 -> -1.0635079 | N30: =N27*Assumptions!C33 -> 0.46688969 | O30: =O27*Assumptions!C33 -> 1.623269 | P30: =P27*Assumptions!C33 -> 2.7178495 | Q30: =Q27*Assumptions!C33 -> 38.808278 | R30: =R27*Assumptions!C33 -> 36.64466 | S30: =S27*Assumptions!C33 -> 34.396743 | T30: =T27*Assumptions!C33 -> 32.056283 | U30: =U27*Assumptions!C33 -> 29.614628 | V30: =V27*Assumptions!C33 -> 27.06269 | W30: =W27*Assumptions!C33 -> 24.390914
B31: Cumulative Distributions | C31: $M | D31: =D30 -> -22.846635 | E31: =D31+E30 -> -65.70414 | F31: =E31+F30 -> -149.68129 | G31: =F31+G30 -> -150.99544 | H31: =G31+H30 -> -150.17102 | I31: =H31+I30 -> -140.76542 | J31: =I31+J30 -> -130.73874 | K31: =J31+K30 -> -135.46187 | L31: =K31+L30 -> -138.32506 | ... W31: =V31+W30 -> 88.393633
B33: KEY METRICS
B34: EBITDA Margin | C34: % | D34: =IF(D5=0,"-",D7/D5) -> - | E34: =IF(E5=0,"-",E7/E5) -> - | F34: =IF(F5=0,"-",F7/F5) -> -0.25651928 | G34: =IF(G5=0,"-",G7/G5) -> 0.266548 | H34: =IF(H5=0,"-",H7/H5) -> 0.40527654 | I34: =IF(I5=0,"-",I7/I5) -> 0.43350418 | J34: =IF(J5=0,"-",J7/J5) -> 0.41905574 | K34: =IF(K5=0,"-",K7/K5) -> 0.40423709 | ... W34: =IF(W5=0,"-",W7/W5) -> 0.1915787
B35: DSCR | C35: x | D35: ='Financing Structure'!D41 -> -1.2834225 | E35: ='Financing Structure'!E41 -> -0.42780749 | F35: ='Financing Structure'!F41 -> -1.0982882 | G35: ='Financing Structure'!G41 -> 0.96716407 | H35: ='Financing Structure'!H41 -> 1.0130693 | I35: ='Financing Structure'!I41 -> 1.1568457 | J35: ='Financing Structure'!J41 -> 1.1763572 | K35: ='Financing Structure'!K41 -> 0.93847985 | ... W35: ='Financing Structure'!W41 -> -
B36: Debt / EBITDA | C36: x | D36: =IF(D7=0,"-",'Financing Structure'!D37/D7) -> -18.333333 | E36: =IF(E7=0,"-",'Financing Structure'!E37/E7) -> -36.666667 | F36: =IF(F7=0,"-",'Financing Structure'!F37/F7) -> -17.546673 | G36: =IF(G7=0,"-",'Financing Structure'!G37/G7) -> 8.4336529 | H36: =IF(H7=0,"-",'Financing Structure'!H37/H7) -> 3.8604735 | I36: =IF(I7=0,"-",'Financing Structure'!I37/I7) -> 3.1508715 | J36: =IF(J7=0,"-",'Financing Structure'!J37/J7) -> 2.7860751 | K36: =IF(K7=0,"-",'Financing Structure'!K37/K7) -> 2.3988419 | ... W36: =IF(W7=0,"-",'Financing Structure'!W37/W7) -> 0
B37: Cumulative Cash Flow | C37: $M | D37: =D27 -> -1.523109 | E37: =D37+E27 -> -4.380276 | F37: =E37+F27 -> -9.9787523 | G37: =F37+G27 -> -10.066362 | H37: =G37+H27 -> -10.011402 | I37: =H37+I27 -> -9.3843616 | J37: =I37+J27 -> -8.7159161 | K37: =J37+K27 -> -9.0307915 | L37: =K37+L27 -> -9.2216709 | ... W37: =V37+W27 -> 5.8929088

Sheet Currency & FX
B1: CURRENCY RISK & CROSS-BORDER TRANSACTION MODEL
B3: FX Component | D3: 1 | E3: 2 | F3: 3 | G3: 4 | H3: 5 | I3: 6 | J3: 7 | K3: 8 | L3: 9 | M3: 10 | N3: 11 | O3: 12 | P3: 13 | Q3: 14 | R3: 15 | S3: 16 | T3: 17 | U3: 18 | V3: 19 | W3: 20
B4: EXCHANGE RATE PROJECTIONS
B5: Spot Rate (Local/USD) — Base | D5: 100 | E5: =D5*(1+Assumptions!C18) -> 105 | F5: =E5*(1+Assumptions!C18) -> 110.25 | G5: =F5*(1+Assumptions!C18) -> 115.7625 | H5: =G5*(1+Assumptions!C18) -> 121.55062 | I5: =H5*(1+Assumptions!C18) -> 127.62816 | J5: =I5*(1+Assumptions!C18) -> 134.00956 | K5: =J5*(1+Assumptions!C18) -> 140.71004 | L5: =K5*(1+Assumptions!C18) -> 147.74554 | M5: =L5*(1+Assumptions!C18) -> 155.13282 | N5: =M5*(1+Assumptions!C18) -> 162.88946 | O5: =N5*(1+Assumptions!C18) -> 171.03394 | P5: =O5*(1+Assumptions!C18) -> 179.58563 | Q5: =P5*(1+Assumptions!C18) -> 188.56491 | R5: =Q5*(1+Assumptions!C18) -> 197.99316 | S5: =R5*(1+Assumptions!C18) -> 207.89282 | T5: =S5*(1+Assumptions!C18) -> 218.28746 | U5: =T5*(1+Assumptions!C18) -> 229.20183 | V5: =U5*(1+Assumptions!C18) -> 240.66192 | W5: =V5*(1+Assumptions!C18) -> 252.69502
B6: Forward Rate (PPP-based) | D6: =100*(1+Assumptions!C18)^0/(1+Assumptions!C17)^0 -> 100 | E6: =100*(1+Assumptions!C18)^1/(1+Assumptions!C17)^1 -> 102.43902 | F6: =100*(1+Assumptions!C18)^2/(1+Assumptions!C17)^2 -> 104.93754 | G6: =100*(1+Assumptions!C18)^3/(1+Assumptions!C17)^3 -> 107.49699 | H6: =100*(1+Assumptions!C18)^4/(1+Assumptions!C17)^4 -> 110.11887 | I6: =100*(1+Assumptions!C18)^5/(1+Assumptions!C17)^5 -> 112.80469 | J6: =100*(1+Assumptions!C18)^6/(1+Assumptions!C17)^6 -> 115.55603 | K6: =100*(1+Assumptions!C18)^7/(1+Assumptions!C17)^7 -> 118.37447 | L6: =100*(1+Assumptions!C18)^8/(1+Assumptions!C17)^8 -> 121.26165 | M6: =100*(1+Assumptions!C18)^9/(1+Assumptions!C17)^9 -> 124.21925 | N6: =100*(1+Assumptions!C18)^10/(1+Assumptions!C17)^10 -> 127.24899 | O6: =100*(1+Assumptions!C18)^11/(1+Assumptions!C17)^11 -> 130.35262 | P6: =100*(1+Assumptions!C18)^12/(1+Assumptions!C17)^12 -> 133.53195 | Q6: =100*(1+Assumptions!C18)^13/(1+Assumptions!C17)^13 -> 136.78883 | R6: =100*(1+Assumptions!C18)^14/(1+Assumptions!C17)^14 -> 140.12514 | S6: =100*(1+Assumptions!C18)^15/(1+Assumptions!C17)^15 -> 143.54283 | T6: =100*(1+Assumptions!C18)^16/(1+Assumptions!C17)^16 -> 147.04387 | U6: =100*(1+Assumptions!C18)^17/(1+Assumptions!C17)^17 -> 150.63031 | V6: =100*(1+Assumptions!C18)^18/(1+Assumptions!C17)^18 -> 154.30422 | W6: =100*(1+Assumptions!C18)^19/(1+Assumptions!C17)^19 -> 158.06774
B7: Stressed Rate (Downside) | D7: =100*(1+Assumptions!D18)^0 -> 100 | E7: =100*(1+Assumptions!D18)^1 -> 110 | F7: =100*(1+Assumptions!D18)^2 -> 121 | G7: =100*(1+Assumptions!D18)^3 -> 133.1 | H7: =100*(1+Assumptions!D18)^4 -> 146.41 | I7: =100*(1+Assumptions!D18)^5 -> 161.051 | J7: =100*(1+Assumptions!D18)^6 -> 177.1561 | K7: =100*(1+Assumptions!D18)^7 -> 194.87171 | L7: =100*(1+Assumptions!D18)^8 -> 214.35888 | M7: =100*(1+Assumptions!D18)^9 -> 235.79477 | N7: =100*(1+Assumptions!D18)^10 -> 259.37425 | O7: =100*(1+Assumptions!D18)^11 -> 285.31167 | P7: =100*(1+Assumptions!D18)^12 -> 313.84284 | Q7: =100*(1+Assumptions!D18)^13 -> 345.22712 | R7: =100*(1+Assumptions!D18)^14 -> 379.74983 | S7: =100*(1+Assumptions!D18)^15 -> 417.72482 | T7: =100*(1+Assumptions!D18)^16 -> 459.4973 | U7: =100*(1+Assumptions!D18)^17 -> 505.44703 | V7: =100*(1+Assumptions!D18)^18 -> 555.99173 | W7: =100*(1+Assumptions!D18)^19 -> 611.5909
B8: Hedged Rate (if applicable)
B10: REVENUE CURRENCY SPLIT
B11: % Revenue in USD (hard currency) | D11: 0.6 | E11: 0.6 | F11: 0.6 | G11: 0.6 | H11: 0.6 | I11: 0.6 | J11: 0.6 | K11: 0.6 | L11: 0.6 | M11: 0.6 | N11: 0.6 | O11: 0.6 | P11: 0.6 | Q11: 0.6 | R11: 0.6 | S11: 0.6 | T11: 0.6 | U11: 0.6 | V11: 0.6 | W11: 0.6
B12: % Revenue in Local Currency | D12: =1-D11 -> 0.4 | E12: =1-E11 -> 0.4 | F12: =1-F11 -> 0.4 | G12: =1-G11 -> 0.4 | H12: =1-H11 -> 0.4 | I12: =1-I11 -> 0.4 | J12: =1-J11 -> 0.4 | K12: =1-K11 -> 0.4 | ... W12: =1-W11 -> 0.4
B13: Effective Blended Revenue ($M, USD) | D13: ='Revenue Build'!D15*(D11+D12*(100/D5)) -> 0 | E13: ='Revenue Build'!E15*(E11+E12*(100/E5)) -> 0 | F13: ='Revenue Build'!F15*(F11+F12*(100/F5)) -> 8.0280164 | G13: ='Revenue Build'!G15*(G11+G12*(100/G5)) -> 15.785855 | H13: ='Revenue Build'!H15*(H11+H12*(100/H5)) -> 19.810282 | I13: ='Revenue Build'!I15*(I11+I12*(100/I5)) -> 19.519971 | J13: ='Revenue Build'!J15*(J11+J12*(100/J5)) -> 19.254718 | K13: ='Revenue Build'!K15*(K11+K12*(100/K5)) -> 19.0133 | ... W13: ='Revenue Build'!W15*(W11+W12*(100/W5)) -> 17.633813
B15: COST CURRENCY SPLIT
B16: % OPEX in USD | D16: 0.35 | E16: 0.35 | F16: 0.35 | G16: 0.35 | H16: 0.35 | I16: 0.35 | J16: 0.35 | K16: 0.35 | L16: 0.35 | M16: 0.35 | N16: 0.35 | O16: 0.35 | P16: 0.35 | Q16: 0.35 | R16: 0.35 | S16: 0.35 | T16: 0.35 | U16: 0.35 | V16: 0.35 | W16: 0.35
B17: % OPEX in Local Currency | D17: =1-D16 -> 0.65 | E17: =1-E16 -> 0.65 | F17: =1-F16 -> 0.65 | G17: =1-G16 -> 0.65 | H17: =1-H16 -> 0.65 | I17: =1-I16 -> 0.65 | J17: =1-J16 -> 0.65 | K17: =1-K16 -> 0.65 | ... W17: =1-W16 -> 0.65
B18: Natural Hedge Ratio | D18: =MIN(D12,D17) -> 0.4 | E18: =MIN(E12,E17) -> 0.4 | F18: =MIN(F12,F17) -> 0.4 | G18: =MIN(G12,G17) -> 0.4 | H18: =MIN(H12,H17) -> 0.4 | I18: =MIN(I12,I17) -> 0.4 | J18: =MIN(J12,J17) -> 0.4 | K18: =MIN(K12,K17) -> 0.4 | ... W18: =MIN(W12,W17) -> 0.4
B20: CROSS-BORDER TRANSACTION COSTS
B21: Wire Transfer / SWIFT Fees ($M) | D21: 0.01 | E21: 0.01 | F21: 0.01 | G21: 0.01 | H21: 0.01 | I21: 0.01 | J21: 0.01 | K21: 0.01 | L21: 0.01 | M21: 0.01 | N21: 0.01 | O21: 0.01 | P21: 0.01 | Q21: 0.01 | R21: 0.01 | S21: 0.01 | T21: 0.01 | U21: 0.01 | V21: 0.01 | W21: 0.01
B22: Currency Conversion Spread | D22: ='Revenue Build'!D15*0.005 -> 0 | E22: ='Revenue Build'!E15*0.005 -> 0 | F22: ='Revenue Build'!F15*0.005 -> 0.041690476 | G22: ='Revenue Build'!G15*0.005 -> 0.083475782 | H22: ='Revenue Build'!H15*0.005 -> 0.10661224 | I22: ='Revenue Build'!I15*0.005 -> 0.10685213 | J22: ='Revenue Build'!J15*0.005 -> 0.10715089 | K22: ='Revenue Build'!K15*0.005 -> 0.10750814 | ... W22: ='Revenue Build'!W15*0.005 -> 0.116273
B23: Capital Repatriation Tax | D23: ='Cash Flow Waterfall'!D30*0.02 -> -0.4569327 | E23: ='Cash Flow Waterfall'!E30*0.02 -> -0.8571501 | F23: ='Cash Flow Waterfall'!F30*0.02 -> -1.6795429 | G23: ='Cash Flow Waterfall'!G30*0.02 -> -0.026283024 | H23: ='Cash Flow Waterfall'!H30*0.02 -> 0.016488258 | I23: ='Cash Flow Waterfall'!I30*0.02 -> 0.188112 | J23: ='Cash Flow Waterfall'!J30*0.02 -> 0.20053365 | K23: ='Cash Flow Waterfall'!K30*0.02 -> -0.094462628 | ... W23: ='Cash Flow Waterfall'!W30*0.02 -> 0.48781828
B24: FX Hedging Premium (NDF/swap) | D24: ='Revenue Build'!D15*(1-D11)*0.02 -> 0 | E24: ='Revenue Build'!E15*(1-E11)*0.02 -> 0 | F24: ='Revenue Build'!F15*(1-F11)*0.02 -> 0.066704762 | G24: ='Revenue Build'!G15*(1-G11)*0.02 -> 0.13356125 | H24: ='Revenue Build'!H15*(1-H11)*0.02 -> 0.17057959 | I24: ='Revenue Build'!I15*(1-I11)*0.02 -> 0.17096341 | J24: ='Revenue Build'!J15*(1-J11)*0.02 -> 0.17144142 | K24: ='Revenue Build'!K15*(1-K11)*0.02 -> 0.17201303 | ... W24: ='Revenue Build'!W15*(1-W11)*0.02 -> 0.18603679
B25: Total Cross-Border Costs ($M) | D25: =D21+D22+D23+D24 -> -0.4469327 | E25: =E21+E22+E23+E24 -> -0.8471501 | F25: =F21+F22+F23+F24 -> -1.5611477 | G25: =G21+G22+G23+G24 -> 0.20075401 | H25: =H21+H22+H23+H24 -> 0.30368009 | I25: =I21+I22+I23+I24 -> 0.47592754 | J25: =J21+J22+J23+J24 -> 0.48912597 | K25: =K21+K22+K23+K24 -> 0.19505854 | ... W25: =W21+W22+W23+W24 -> 0.80012807
B27: FX IMPACT ANALYSIS
B28: Unhedged FX P&L Impact ($M) | D28: ='Revenue Build'!D15*D12*(1-100/D5) -> 0 | E28: ='Revenue Build'!E15*E12*(1-100/E5) -> 0 | F28: ='Revenue Build'!F15*F12*(1-100/F5) -> 0.31007883 | G28: ='Revenue Build'!G15*G12*(1-100/G5) -> 0.90930104 | H28: ='Revenue Build'!H15*H12*(1-100/H5) -> 1.512167 | I28: ='Revenue Build'!I15*I12*(1-100/I5) -> 1.8504553 | J28: ='Revenue Build'!J15*J12*(1-100/J5) -> 2.1754597 | K28: ='Revenue Build'!K15*K12*(1-100/K5) -> 2.488329 | ... W28: ='Revenue Build'!W15*W12*(1-100/W5) -> 5.6207858
B29: Net FX Exposure After Hedging ($M) | D29: =D28*(1-D18) -> 0 | E29: =E28*(1-E18) -> 0 | F29: =F28*(1-F18) -> 0.1860473 | G29: =G28*(1-G18) -> 0.54558062 | H29: =H28*(1-H18) -> 0.90730017 | I29: =I28*(1-I18) -> 1.1102732 | J29: =J28*(1-J18) -> 1.3052758 | K29: =K28*(1-K18) -> 1.4929974 | ... W29: =W28*(1-W18) -> 3.3724715
B30: Cumulative FX Impact ($M) | D30: =D29 -> 0 | E30: =D30+E29 -> 0 | F30: =E30+F29 -> 0.1860473 | G30: =F30+G29 -> 0.73162792 | H30: =G30+H29 -> 1.6389281 | I30: =H30+I29 -> 2.7492013 | J30: =I30+J29 -> 4.0544771 | K30: =J30+K29 -> 5.5474745 | L30: =K30+L29 -> 7.2215536 | ... W30: =V30+W29 -> 36.211863

Sheet Returns Analysis
B1: RETURNS ANALYSIS — IRR, NPV, MOIC
B3: PROJECT-LEVEL RETURNS
B4: Metric | C4: Base Case | D4: Downside | E4: Upside | F4: Unit
B5: Project Unlevered IRR | C5: IRR calc | D5: IRR calc | E5: IRR calc | F5: %
B6: Project NPV @ WACC ($M) | C6: NPV calc | D6: NPV calc | E6: NPV calc | F6: $M
B7: Project MOIC (unlevered) | C7: MOIC calc | D7: MOIC calc | E7: MOIC calc | F7: x
B8: Payback Period (years) | C8: Payback | D8: Payback | E8: Payback | F8: yrs
B10: IRR CASH FLOW ARRAY (for manual IRR calculation)
B11: Year | C11: Project CF | D11: Equity CF | E11: Fund CF
B12: 0 | C12: =-'CAPEX Schedule'!C29 -> -57.072 | D12: =-Assumptions!C33 -> -15 | E12: =-Assumptions!C33 -> -15
B13: 1 | C13: ='Cash Flow Waterfall'!D14 -> -0.85608 | D13: ='Cash Flow Waterfall'!D27 -> -1.523109 | E13: ='Cash Flow Waterfall'!D30 -> -22.846635
B14: 2 | C14: ='Cash Flow Waterfall'!E14 -> -0.85608 | D14: ='Cash Flow Waterfall'!E27 -> -2.857167 | E14: ='Cash Flow Waterfall'!E30 -> -42.857505
B15: 3 | C15: ='Cash Flow Waterfall'!F14 -> -2.9303603 | D15: ='Cash Flow Waterfall'!F27 -> -5.5984763 | E15: ='Cash Flow Waterfall'!F30 -> -83.977145
B16: 4 | C16: ='Cash Flow Waterfall'!G14 -> 2.5805059 | D16: ='Cash Flow Waterfall'!G27 -> -0.087610079 | E16: ='Cash Flow Waterfall'!G30 -> -1.3141512
B17: 5 | C17: ='Cash Flow Waterfall'!H14 -> 6.0861362 | D17: ='Cash Flow Waterfall'!H27 -> 0.05496086 | E17: ='Cash Flow Waterfall'!H30 -> 0.8244129
B18: 6 | C18: ='Cash Flow Waterfall'!I14 -> 6.6069347 | D18: ='Cash Flow Waterfall'!I27 -> 0.62703999 | E18: ='Cash Flow Waterfall'!I30 -> 9.4055998
B19: 7 | C19: ='Cash Flow Waterfall'!J14 -> 6.3696282 | D19: ='Cash Flow Waterfall'!J27 -> 0.66844551 | E19: ='Cash Flow Waterfall'!J30 -> 10.026683
B20: 8 | C20: ='Cash Flow Waterfall'!K14 -> 4.8033732 | D20: ='Cash Flow Waterfall'!K27 -> -0.31487543 | E20: ='Cash Flow Waterfall'!K30 -> -4.7231314
B21: 9 | C21: ='Cash Flow Waterfall'!L14 -> 4.630912 | D21: ='Cash Flow Waterfall'!L27 -> -0.19087938 | E21: ='Cash Flow Waterfall'!L30 -> -2.8631906
B22: 10 | C22: ='Cash Flow Waterfall'!M14 -> 4.4544335 | D22: ='Cash Flow Waterfall'!M27 -> -0.070900524 | E22: ='Cash Flow Waterfall'!M30 -> -1.0635079
B23: 11 | C23: ='Cash Flow Waterfall'!N14 -> 4.2733424 | D23: ='Cash Flow Waterfall'!N27 -> 0.031125979 | E23: ='Cash Flow Waterfall'!N30 -> 0.46688969
B24: 12 | C24: ='Cash Flow Waterfall'!O14 -> 4.0870164 | D24: ='Cash Flow Waterfall'!O27 -> 0.10821793 | E24: ='Cash Flow Waterfall'!O30 -> 1.623269
B25: 13 | C25: ='Cash Flow Waterfall'!P14 -> 3.8948048 | D25: ='Cash Flow Waterfall'!P27 -> 0.18118997 | E25: ='Cash Flow Waterfall'!P30 -> 2.7178495
B26: 14 | C26: ='Cash Flow Waterfall'!Q14 -> 3.6960264 | D26: ='Cash Flow Waterfall'!Q27 -> 2.5872185 | E26: ='Cash Flow Waterfall'!Q30 -> 38.808278
B27: 15 | C27: ='Cash Flow Waterfall'!R14 -> 3.4899676 | D27: ='Cash Flow Waterfall'!R27 -> 2.4429774 | E27: ='Cash Flow Waterfall'!R30 -> 36.64466
B28: 16 | C28: ='Cash Flow Waterfall'!S14 -> 3.2758802 | D28: ='Cash Flow Waterfall'!S27 -> 2.2931162 | E28: ='Cash Flow Waterfall'!S30 -> 34.396743
B29: 17 | C29: ='Cash Flow Waterfall'!T14 -> 3.0529793 | D29: ='Cash Flow Waterfall'!T27 -> 2.1370855 | E29: ='Cash Flow Waterfall'!T30 -> 32.056283
B30: 18 | C30: ='Cash Flow Waterfall'!U14 -> 2.8204408 | D30: ='Cash Flow Waterfall'!U27 -> 1.9743085 | E30: ='Cash Flow Waterfall'!U30 -> 29.614628
B31: 19 | C31: ='Cash Flow Waterfall'!V14 -> 2.577399 | D31: ='Cash Flow Waterfall'!V27 -> 1.8041793 | E31: ='Cash Flow Waterfall'!V30 -> 27.06269
B32: 20 | C32: ='Cash Flow Waterfall'!W14 -> 2.3229442 | D32: ='Cash Flow Waterfall'!W27 -> 1.6260609 | E32: ='Cash Flow Waterfall'!W30 -> 24.390914
B34: IRR | C34: =IFERROR(IRR(C12:C32),"-") -> 0.010628432 | D34: =IFERROR(IRR(D12:D32),"-") -> -0.029294227 | E34: =IFERROR(IRR(E12:E32),"-") -> 0.027066299
B35: MOIC | C35: =IFERROR(SUM(C13:C32)/-C12,"-") -> 1.1280524 | D35: =IFERROR(SUM(D13:D32)/-D12,"-") -> 0.39286059 | E35: =IFERROR(SUM(E13:E32)/-E12,"-") -> 5.8929088
B36: NPV @ 10% | C36: =IFERROR(NPV(0.1,C13:C32)+C12,"-") -> -33.969731 | D36: =IFERROR(NPV(0.1,D13:D32)+D12,"-") -> -19.358425 | E36: =IFERROR(NPV(0.1,E13:E32)+E12,"-") -> -80.376368

Sheet Exit Scenarios
B1: EXIT SCENARIO ANALYSIS
B3: EXIT TIMING & MULTIPLES
B4: Parameter | C4: Year 5 | D4: Year 7 | E4: Year 10 | F4: Year 12 | G4: Year 15
B5: Exit EBITDA Multiple (x) | C5: 6 | D5: 7 | E5: 8 | F5: 7.5 | G5: 7
B6: Projected EBITDA at Exit ($M) | C6: ='Cash Flow Waterfall'!H7 -> 7.2275762 | D6: ='Cash Flow Waterfall'!J7 -> 7.5110682 | E6: ='Cash Flow Waterfall'!M7 -> 6.7711335 | F6: ='Cash Flow Waterfall'!O7 -> 6.246252 | G6: ='Cash Flow Waterfall'!R7 -> 5.3933252
B7: Enterprise Value at Exit ($M) | C7: =C5*C6 -> 43.365457 | D7: =D5*D6 -> 52.577477 | E7: =E5*E6 -> 54.169068 | F7: =F5*F6 -> 46.84689 | G7: =G5*G6 -> 37.753276
B8: Less: Net Debt at Exit ($M) | C8: =-'Financing Structure'!H37 -> -27.901867 | D8: =-'Financing Structure'!J37 -> -20.9264 | E8: =-'Financing Structure'!M37 -> -10.4632 | F8: =-'Financing Structure'!O37 -> -3.4877333 | G8: =-'Financing Structure'!R37 -> 0
B9: Equity Value ($M) | C9: =C7+C8 -> 15.46359 | D9: =D7+D8 -> 31.651077 | E9: =E7+E8 -> 43.705868 | F9: =F7+F8 -> 43.359156 | G9: =G7+G8 -> 37.753276
B10: Fund's Share of Equity Value ($M) | C10: =C9*Assumptions!C34 -> 4.6390771 | D10: =D9*Assumptions!C34 -> 9.4953231 | E10: =E9*Assumptions!C34 -> 13.11176 | F10: =F9*Assumptions!C34 -> 13.007747 | G10: =G9*Assumptions!C34 -> 11.325983
B11: Plus: Cumulative Distributions ($M) | C11: ='Cash Flow Waterfall'!H31 -> -150.17102 | D11: ='Cash Flow Waterfall'!J31 -> -130.73874 | E11: ='Cash Flow Waterfall'!M31 -> -139.38857 | F11: ='Cash Flow Waterfall'!O31 -> -137.29841 | G11: ='Cash Flow Waterfall'!R31 -> -59.127625
B12: Total Fund Proceeds ($M) | C12: =C10+C11 -> -145.53195 | D12: =D10+D11 -> -121.24342 | E12: =E10+E11 -> -126.27681 | F12: =F10+F11 -> -124.29067 | G12: =G10+G11 -> -47.801642
B15: EXIT TYPE COMPARISON
C16: Trade Sale | D16: Secondary PE | E16: IPO | F16: Recapitalization | G16: Liquidation
B17: Probability Weighting | C17: 0.35 | D17: 0.25 | E17: 0.15 | F17: 0.15 | G17: 0.1
B18: EBITDA Multiple Adjustment | C18: 1 | D18: 0.9 | E18: 1.15 | F18: 0.85 | G18: 0.5
B19: Transaction Cost (%) | C19: 0.03 | D19: 0.02 | E19: 0.07 | F19: 0.025 | G19: 0.05
B20: Time to Close (months) | C20: 6 | D20: 4 | E20: 12 | F20: 3 | G20: 9
B21: Tax Efficiency Factor | C21: 0.95 | D21: 0.9 | E21: 0.85 | F21: 0.92 | G21: 0.8
B23: RETURNS BY EXIT TYPE (Base Case: Year 7 Exit)
C24: Trade Sale | D24: Secondary PE | E24: IPO | F24: Recapitalization | G24: Liquidation
B25: Adjusted EV ($M)
B26: Net Equity to Fund ($M)
B27: Fund MOIC
B28: Fund IRR (approx)
B29: Probability-Weighted Return ($M)

Sheet Sensitivity
B1: SENSITIVITY & SCENARIO ANALYSIS
B3: TWO-WAY DATA TABLE: EQUITY IRR
B4: Revenue Growth → | C4: -0.1 | D4: -0.05 | E4: 0 | F4: 0.05 | G4: 0.1 | H4: 0.15
B5: OPEX % ↓
B6: 0.35 | C6: IRR | D6: IRR | E6: IRR | F6: IRR | G6: IRR | H6: IRR
B7: 0.4 | C7: IRR | D7: IRR | E7: IRR | F7: IRR | G7: IRR | H7: IRR
B8: 0.45 | C8: IRR | D8: IRR | E8: IRR | F8: IRR | G8: IRR | H8: IRR
B9: 0.5 | C9: IRR | D9: IRR | E9: IRR | F9: IRR | G9: IRR | H9: IRR
B10: 0.55 | C10: IRR | D10: IRR | E10: IRR | F10: IRR | G10: IRR | H10: IRR
B11: 0.6 | C11: IRR | D11: IRR | E11: IRR | F11: IRR | G11: IRR | H11: IRR
B15: TORNADO CHART DATA — KEY DRIVER SENSITIVITIES
B16: Variable | C16: Low Value | D16: Base Value | E16: High Value | F16: IRR at Low | G16: IRR at High | H16: IRR Swing
B17: Commodity Price (±20%) | C17: -0.2 | D17: 0 | E17: 0.2 | F17: calc | G17: calc | H17: calc
B18: FX Depreciation Rate | C18: 0.02 | D18: 0.05 | E18: 0.1 | F18: calc | G18: calc | H18: calc
B19: OPEX as % Revenue | C19: 0.35 | D19: 0.45 | E19: 0.55 | F19: calc | G19: calc | H19: calc
B20: Utilization Rate | C20: 0.7 | D20: 0.85 | E20: 0.95 | F20: calc | G20: calc | H20: calc
B21: Senior Debt Rate | C21: 0.07 | D21: 0.085 | E21: 0.1 | F21: calc | G21: calc | H21: calc
B22: Construction Overrun (%) | C22: 0 | D22: 0 | E22: 0.2 | F22: calc | G22: calc | H22: calc
B23: Tax Rate | C23: 0.25 | D23: 0.3 | E23: 0.35 | F23: calc | G23: calc | H23: calc
B24: Exit Multiple | C24: 5 | D24: 7 | E24: 9 | F24: calc | G24: calc | H24: calc
B27: SCENARIO SUMMARY TABLE
B28: Scenario | C28: Project IRR | D28: Equity IRR | E28: Fund MOIC | F28: DSCR (Min) | G28: NPV ($M)
B29: Base Case | C29: [scenario calc] | D29: [scenario calc] | E29: [scenario calc] | F29: [scenario calc] | G29: [scenario calc]
B30: Downside: Low Commodity + High FX | C30: [scenario calc] | D30: [scenario calc] | E30: [scenario calc] | F30: [scenario calc] | G30: [scenario calc]
B31: Downside: Construction Delay + Cost Overrun | C31: [scenario calc] | D31: [scenario calc] | E31: [scenario calc] | F31: [scenario calc] | G31: [scenario calc]
B32: Upside: High Utilization + Favorable FX | C32: [scenario calc] | D32: [scenario calc] | E32: [scenario calc] | F32: [scenario calc] | G32: [scenario calc]
B33: Stress: Combined Adverse Scenario | C33: [scenario calc] | D33: [scenario calc] | E33: [scenario calc] | F33: [scenario calc] | G33: [scenario calc]
B34: Blue Sky: Full Capacity + Bull Commodity | C34: [scenario calc] | D34: [scenario calc] | E34: [scenario calc] | F34: [scenario calc] | G34: [scenario calc]

Sheet Impact Metrics
B1: IMPACT METRICS & IRIS+ ALIGNMENT
B3: IMPACT KPIs — LINKED TO CARRIED INTEREST
B4: Impact Metric | C4: Target | D4: Threshold | E4: Achieved | F4: IRIS+ Code
B5: Direct Jobs Created (#) | C5: 500 | D5: 250 | E5: 0 | F5: PI1439
B6: Local Procurement (% of total spend) | C6: 0.4 | D6: 0.25 | E6: 0 | F6: PI2822
B7: CO2 Emissions Avoided (tCO2e/yr) | C7: 15000 | D7: 5000 | E7: 0 | F7: PI1479
B8: Community Health Beneficiaries (#) | C8: 5000 | D8: 2000 | E8: 0 | F8: PI8718
B9: Women in Workforce (%) | C9: 0.3 | D9: 0.2 | E9: 0 | F9: PI4060
B10: Skills Training Graduates (#) | C10: 200 | D10: 100 | E10: 0 | F10: PI3687
B11: Water Efficiency Improvement (%) | C11: 0.25 | D11: 0.1 | E11: 0 | F11: PI2094
B12: Local Tax Revenue Generated ($M/yr) | C12: 2 | D12: 1 | E12: 0 | F12: PI6424
B13: Energy Access Connections (#) | C13: 10000 | D13: 3000 | E13: 0 | F13: PI2564
B14: Biodiversity Net Gain (hectares) | C14: 50 | D14: 20 | E14: 0 | F14: PI8838
B17: IMPACT-LINKED CARRY MECHANISM
B18: Base Carried Interest | C18: 0.2
B19: Impact-Linked Portion (% of carry) | C19: 0.05
B20: Impact Score (0-100%) | C20: 0
B21: Adjusted Carry Rate | C21: 0.2
B22: Impact Bonus / Malus ($M) | C22: 0.05
C23: 0
C24: =IF(C23>0,C21*(1-C22*(1-C23)),C21) -> 0.2
B25: UN SDG ALIGNMENT | C25: =(C21-C24)*100 -> 0
B26: SDG | C26: Alignment
B27: SDG 7: Affordable & Clean Energy | C27: Primary
B28: SDG 8: Decent Work & Economic Growth | C28: Primary
B29: SDG 9: Industry, Innovation & Infrastructure | C29: Primary
B30: SDG 11: Sustainable Cities & Communities | C30: Secondary
B31: SDG 12: Responsible Consumption & Production | C31: Secondary
B32: SDG 13: Climate Action | C32: Secondary
